Workbook

Sheet Valuation_Summary
C2: Company Name: | D2: Name | E2: Compass Group
C3: Ticker: | D3: Name | E3: CPG
C4: Valuation Date: | D4: Date | E4: 46241
C5: Last Historical Year: | D5: Date | E5: 45930
C6: Current Share Price: | D6: $ | E6: 31.71
C7: Status: | E7: Overvalued
C10: Headline KPIs | AA10: =TEXT(ABS(DCF!J29), "0.0%") & IF(DCF!J29<0, " Discount to Current", " Premium to Current") -> 10.8% Discount to Current
AA11: =TEXT(ABS((Public_Comps!H41/Public_Comps!H37)-1), "0.0%") & " Premium to Peers" -> 55.1% Premium to Peers
AA12: =TEXT(Public_Comps!H41, "0.0") & "x vs. " & TEXT(Public_Comps!H37, "0.0") & "x" -> 13.9x vs. 9.0x
AA13: =TEXT(LBO!H294, "0.0%") & " IRR / " & TEXT(LBO!H300, "0.0") & "x MoIC" -> 4.9% IRR / 1.3x MoIC
AD15: Min | AE15: 25th | AF15: Median | AG15: 75th | AH15: Max | AI15: Min Point | AJ15: 25th Point | AK15: Median Point | AL15: 75th Point | AM15: Max Point
AA17: DCF Perpetuity Growth Rate Method: | AD17: =DCF!O109 -> 18.118906 | AE17: =DCF!M107 -> 20.41064 | AF17: =DCF!J104 -> 24.97781 | AG17: =DCF!G101 -> 31.793167 | AH17: =DCF!E99 -> 39.10368 | AI17: =AD17 -> 18.118906 | AJ17: =AE17-AD17 -> 2.2917339 | AK17: =AF17-AE17 -> 4.5671704 | AL17: =AG17-AF17 -> 6.8153566 | AM17: =AH17-AG17 -> 7.3105132
AA18: DCF Multiple Method: | AD18: =DCF!O94 -> 23.051381 | AE18: =DCF!M91 -> 25.307054 | AF18: =DCF!J88 -> 27.991631 | AG18: =DCF!G86 -> 30.233767 | AH18: =DCF!E84 -> 32.212554 | AI18: =AD18 -> 23.051381 | AJ18: =AE18-AD18 -> 2.2556727 | AK18: =AF18-AE18 -> 2.6845774 | AL18: =AG18-AF18 -> 2.2421356 | AM18: =AH18-AG18 -> 1.9787871
AA20: LBO: | AD20: =LBO!E305 -> 18 | AE20: =LBO!F305 -> 19.5 | AF20: =LBO!G305 -> 21 | AG20: =LBO!H305 -> 22.5 | AH20: =LBO!I305 -> 24 | AI20: =AD20 -> 18 | AJ20: =AE20-AD20 -> 1.5 | AK20: =AF20-AE20 -> 1.5 | AL20: =AG20-AF20 -> 1.5 | AM20: =AH20-AG20 -> 1.5
AA22: =Public_Comps!B55 -> FY 26 P / E: | AD22: =Public_Comps!M55 -> 17.797362 | AE22: =Public_Comps!L55 -> 19.278951 | AF22: =Public_Comps!K55 -> 33.341245 | AG22: =Public_Comps!J55 -> 36.61241 | AH22: =Public_Comps!I55 -> 39.747279 | AI22: =AD22 -> 17.797362 | AJ22: =AE22-AD22 -> 1.4815892 | AK22: =AF22-AE22 -> 14.062294 | AL22: =AG22-AF22 -> 3.2711649 | AM22: =AH22-AG22 -> 3.1348683
C23: Valuation Output Summary: | AA23: =Public_Comps!B52 -> FY26 TEV / EBITDA: | AD23: =Public_Comps!M52 -> 8.2345367 | AE23: =Public_Comps!L52 -> 8.9668628 | AF23: =Public_Comps!K52 -> 19.184273 | AG23: =Public_Comps!J52 -> 20.267634 | AH23: =Public_Comps!I52 -> 28.745832 | AI23: =AD23 -> 8.2345367 | AJ23: =AE23-AD23 -> 0.73232612 | AK23: =AF23-AE23 -> 10.21741 | AL23: =AG23-AF23 -> 1.0833614 | AM23: =AH23-AG23 -> 8.4781979
AA25: Current Share Price | AD25: =$E$6 -> 31.71 | AE25: =$E$6 -> 31.71 | AF25: =$E$6 -> 31.71 | AG25: =$E$6 -> 31.71 | AH25: =$E$6 -> 31.71 | AI25: 1000 | AJ25: 0 | AK25: =$AJ$25 -> 0 | AL25: =$AJ$25 -> 0 | AM25: =$AJ$25 -> 0
C59: Valuation Methodology | D59: Low ($) | E59: High ($) | F59: Median ($) | G59: Implied TEV ($M) | H59: vs. Spot | I59: Range Parameters
C60: Comps: FY26 EV/EBITDA | D60: =AE23 -> 8.9668628 | E60: =AG23 -> 20.267634 | F60: =AF23 -> 19.184273 | G60: =F60*DCF!$E$9+SUM(DCF!$E$14:$E$19) -> 40565.927 | H60: =F60/$E$6-1 -> -0.39500875 | I60: 25th – 75th Peer Percentile
C61: Comps: FY26 P/E | D61: =AE22 -> 19.278951 | E61: =AG22 -> 36.61241 | F61: =AF22 -> 33.341245 | G61: =F61*DCF!$E$9+SUM(DCF!$E$14:$E$19) -> 65836.123 | H61: =F61/$E$6-1 -> 0.051442616 | I61: 25th – 75th Peer Percentile
C62: LBO: Ability to Pay (15-25% IRR) | D62: =AE20 -> 19.5 | E62: =AG20 -> 22.5 | F62: =AF20 -> 21 | G62: =F62*DCF!$E$9+SUM(DCF!$E$14:$E$19) -> 43807 | H62: =F62/$E$6-1 -> -0.33774834 | I62: Required 25.0% – 15.0% IRR
C63: DCF: Multiple Method | D63: =AE18 -> 25.307054 | E63: =AG18 -> 30.233767 | F63: =AF18 -> 27.991631 | G63: =F63*DCF!$E$9+SUM(DCF!$E$14:$E$19) -> 56287.061 | H63: =F63/$E$6-1 -> -0.11726172 | I63: 9.0x – 11.5x EBITDA Multiple
C64: DCF: Perpetuity Growth | D64: =AE17 -> 20.41064 | E64: =AG17 -> 31.793167 | F64: =AF17 -> 24.97781 | G64: =F64*DCF!$E$9+SUM(DCF!$E$14:$E$19) -> 50907.391 | H64: =F64/$E$6-1 -> -0.21230495 | I64: 3.0% – 4.0% Terminal Growth
C65: Current Share Price | D65: =$E$6 -> 31.71 | E65: =$E$6 -> 31.71 | F65: =$E$6 -> 31.71 | G65: =F65*DCF!$E$9+SUM(DCF!$E$14:$E$19) -> 62924.35 | H65: 0 | I65: Spot Price as of Valuation Date
C69: Core Model Assumptions:
C71: Operating Assumptions: | E71: DCF Assumptions: | H71: LBO Assumptions:
C72: ="5-Yr Revenue Growth: "&TEXT('3_Statment_model'!L9,"0.0%")&" - "&TEXT('3_Statment_model'!H9,"0.0%")&" YoY" -> 5-Yr Revenue Growth: 6.6% - 8.0% YoY | E72: ="Calculated WACC: "&TEXT(DCF!E11,"0.0%") -> Calculated WACC: 8.0% | H72: ="Offer Premium: "&TEXT(LBO!E7,"0.0%") -> Offer Premium: 25.0%
C73: ="Direct Operating Costs: "&TEXT(('3_Statment_model'!J17+'3_Statment_model'!H15),"0.0%") & " of Rev" -> Direct Operating Costs: 90.6% of Rev | E73: ="FCF Terminal Growth Rate: "&TEXT(DCF!O8,"0.0%") -> FCF Terminal Growth Rate: 3.0% | H73: ="Entry Valuation: "&TEXT(LBO!E25,"0.0x")&" TEV / EBITDA" -> Entry Valuation: 17.2x TEV / EBITDA
C74: ="Effective Tax Rate: "&TEXT('3_Statment_model'!H21,"0.0%") -> Effective Tax Rate: 27.7% | E74: ="Terminal EBITDA Multiple: "&TEXT(DCF!J6,"0.0x") -> Terminal EBITDA Multiple: 11.0x | H74: ="Entry Leverage: "&TEXT(LBO!K240,"0.0x")&" Debt / EBITDA" -> Entry Leverage: 6.3x Debt / EBITDA
C75: ="CapEx Requirement: ~"&TEXT('3_Statment_model'!J233,"0.0%") & " of Rev" -> CapEx Requirement: ~3.0% of Rev | E75: ="Unlevered Beta: "&TEXT(DCF!E69,"0.00") -> Unlevered Beta: 0.69 | H75: ="Weighted Debt Cost: "&TEXT((LBO!K173*LBO!D37+LBO!D38*LBO!K174+LBO!K175*LBO!D39)/LBO!K230,"0.0%") -> Weighted Debt Cost: 7.7%
C76: ="NWC Intensity: ~"&TEXT('3_Statment_model'!J234,"0.0%") & " of Rev" -> NWC Intensity: ~35.6% of Rev | E76: ="Risk-Free Rate: "&TEXT(DCF!D52,"0.0%") -> Risk-Free Rate: 4.9% | H76: ="Base Scenario Exit Multiple (FY30): "&TEXT(LBO!N29-1,"0.0x") -> Base Scenario Exit Multiple (FY30): 14.0x
C80: Investment Thesis:

Sheet DCF
B3: DCF Output: | D3: Units:
C5: Company Name: | D5: Name | E5: =Valuation_Summary!E2 -> Compass Group | G5: Terminal Value - Multiples Method: | L5: Terminal Value - Perpetuity Growth Method:
C6: Last Historical Year: | D6: Date | E6: =Valuation_Summary!E5 -> 45930 | G6: Terminal EBITDA Multiple: | J6: 11 | L6: Expected Long-Term Nominal GDP Growth: | O6: 0.04
G7: Projected FY30 EBITDA: | J7: ='3_Statment_model'!L226 -> 6199.9658
C8: Current Share Price: | D8: $ | E8: =Valuation_Summary!E6 -> 31.71 | L8: Baseline Terminal FCF Growth Rate: | O8: 0.03
C9: Diluted Shares Outstanding: | D9: M Shares | E9: 1785 | G9: Baseline Terminal Value: | J9: =J6*J7 -> 68199.624 | L9: Baseline Terminal Value: | O9: =L48*(1+O8)/(E11-O8) -> 63503.263
G10: Implied Terminal FCF Growth Rate: | J10: =(J9*E11-L48)/(J9+L48) -> 0.033311224 | L10: Implied Terminal EBITDA Multiple: | O10: =O9/J7 -> 10.242518
C11: Discount Rate (WACC) | D11: % | E11: =$F$77 -> 0.080270171
G12: (+) PV of Terminal Value: | J12: =J9/(1+$E$11)^5 -> 46357.506 | L12: (+) PV of Terminal Value: | O12: =O9/(1+$E$11)^5 -> 43165.236
C13: Current Equity Value: | D13: $ M | E13: =$E$9*$E$8 -> 56602.35 | G13: (+) PV of UFCFs: | J13: =NPV($E$11,$H$48:$L$48) -> 10469.674 | L13: (+) PV of UFCFs: | O13: =NPV($E$11,$H$48:$L$48) -> 10469.674
C14: (-) Cash & Investments: | D14: $ M | E14: =-'3_Statment_model'!$G$158 -> -575 | G14: Implied Enterprise Value: | J14: =SUM(J12:J13) -> 56827.18 | L14: Implied Enterprise Value: | O14: =SUM(O12:O13) -> 53634.91
C15: (+) Debt: | D15: $ M | E15: =-'3_Statment_model'!$G$165-'3_Statment_model'!$G$172 -> 5426
C16: (+) Preferred Stock: | D16: $ M | E16: 0 | G16: % of Implied TEV from Terminal Value: | J16: =J12/J14 -> 0.81576291 | L16: % of Implied TEV from Terminal Value: | O16: =O12/O14 -> 0.8047974
C17: (+) Leases: | D17: $ M | E17: =-'3_Statment_model'!$G$166-'3_Statment_model'!$G$173 -> 1566
C18: (+) Noncontrolling Interests: | D18: $ M | E18: ='3_Statment_model'!$G$183 -> 107 | G18: (+) Cash & Investments: | J18: =-E14 -> 575 | L18: (+) Cash & Investments: | O18: =-E14 -> 575
C19: (-) Net Pension Asset: | D19: $ M | E19: -202 | G19: (-) Debt: | J19: =-E15 -> -5426 | L19: (-) Debt: | O19: =-E15 -> -5426
C20: Current Enterprise Value: | D20: $ M | E20: =SUM(E13:E19) -> 62924.35 | G20: (-) Preferred Stock: | J20: =-E16 -> 0 | L20: (-) Preferred Stock: | O20: =-E16 -> 0
G21: (-) Leases: | J21: =-E17 -> -1566 | L21: (-) Leases: | O21: =-E17 -> -1566
G22: (-) Noncontrolling Interests: | J22: =-E18 -> -107 | L22: (-) Noncontrolling Interests: | O22: =-E18 -> -107
G23: (+) Net Pension Asset: | J23: =-E19 -> 202 | L23: (+) Net Pension Asset: | O23: =-E19 -> 202
G24: Implied Equity Value: | J24: =SUM(J14,J18:J23) -> 50505.18 | L24: Implied Equity Value: | O24: =SUM(O14,O18:O23) -> 47312.91
G26: Diluted Shares Outstanding: | J26: =E9 -> 1785 | L26: Diluted Shares Outstanding: | O26: =E9 -> 1785
G28: Implied Share Price from DCF: | J28: =J24/J26 -> 28.294218 | L28: Implied Share Price from DCF: | O28: =O24/O26 -> 26.505832
G29: Premium / (Discount) to Current: | J29: =(J28-$E$8)/$E$8 -> -0.10771939 | L29: Premium / (Discount) to Current: | O29: =(O28-$E$8)/$E$8 -> -0.16411757
F31: Historical: | J31: Projected:
B32: Free Cash Flow Projections: | D32: Units: | E32: =EOMONTH(F32,-12) -> 45199 | F32: =EOMONTH(G32,-12) -> 45565 | G32: =E6 -> 45930 | H32: =EOMONTH(G32,12) -> 46295 | I32: =EOMONTH(H32,12) -> 46660 | J32: =EOMONTH(I32,12) -> 47026 | K32: =EOMONTH(J32,12) -> 47391 | L32: =EOMONTH(K32,12) -> 47756
C33: ='3_Statment_model'!C127 -> Revenue: | D33: ='3_Statment_model'!D127 -> $M | E33: ='3_Statment_model'!E127 -> 37907 | F33: ='3_Statment_model'!F127 -> 42002 | G33: ='3_Statment_model'!G127 -> 46070 | H33: ='3_Statment_model'!H127 -> 49755.6 | I33: ='3_Statment_model'!I127 -> 53561.903 | J33: ='3_Statment_model'!J127 -> 57471.922 | ... L33: ='3_Statment_model'!L127 -> 65522.992
C34: ='3_Statment_model'!C128 -> (-) Direct Costs: | D34: ='3_Statment_model'!D128 -> $M | E34: ='3_Statment_model'!E128 -> -12254 | F34: ='3_Statment_model'!F128 -> -13293 | G34: ='3_Statment_model'!G128 -> -14212 | H34: ='3_Statment_model'!H128 -> -15225.214 | I34: ='3_Statment_model'!I128 -> -16282.819 | J34: ='3_Statment_model'!J128 -> -17356.521 | ... L34: ='3_Statment_model'!L128 -> -19656.897
C35: ='3_Statment_model'!C129 -> (-) SG&A: | D35: ='3_Statment_model'!D129 -> $M | E35: ='3_Statment_model'!E129 -> -22175 | F35: ='3_Statment_model'!F129 -> -24711 | G35: ='3_Statment_model'!G129 -> -27373 | H35: ='3_Statment_model'!H129 -> -29654.338 | I35: ='3_Statment_model'!I129 -> -32030.018 | J35: ='3_Statment_model'!J129 -> -34483.153 | ... L35: ='3_Statment_model'!L129 -> -39313.795
C36: ='3_Statment_model'!C130 -> (-) Depreciation and Amortisation: | D36: ='3_Statment_model'!D130 -> $M | E36: ='3_Statment_model'!E130 -> -952 | F36: ='3_Statment_model'!F130 -> -1050 | G36: ='3_Statment_model'!G130 -> -1190 | H36: ='3_Statment_model'!H130 -> -1355.043 | I36: ='3_Statment_model'!I130 -> -1416.4544 | J36: ='3_Statment_model'!J130 -> -1490.9434 | ... L36: ='3_Statment_model'!L130 -> -1672.5334
C37: ='3_Statment_model'!C131 -> (-) Restructuring / Integration: | D37: ='3_Statment_model'!D131 -> $M | E37: ='3_Statment_model'!E131 -> -281 | F37: ='3_Statment_model'!F131 -> -408 | G37: ='3_Statment_model'!G131 -> -368 | H37: ='3_Statment_model'!H131 -> -352.33333 | I37: ='3_Statment_model'!I131 -> -352.33333 | J37: ='3_Statment_model'!J131 -> -352.33333 | ... L37: ='3_Statment_model'!L131 -> -352.33333
C38: ='3_Statment_model'!C132 -> (+) Share of Results of Joint Ventures and Associates: | D38: ='3_Statment_model'!D132 -> $M | E38: ='3_Statment_model'!E132 -> 68 | F38: ='3_Statment_model'!F132 -> 44 | G38: ='3_Statment_model'!G132 -> 37 | H38: ='3_Statment_model'!H132 -> 0 | I38: ='3_Statment_model'!I132 -> 0 | J38: ='3_Statment_model'!J132 -> 0 | ... L38: ='3_Statment_model'!L132 -> 0
C39: ='3_Statment_model'!C133 -> Operating Income (EBIT): | D39: ='3_Statment_model'!D133 -> $M | E39: =SUM(E33:E38) -> 2313 | F39: =SUM(F33:F38) -> 2584 | G39: =SUM(G33:G38) -> 2964 | H39: =SUM(H33:H38) -> 3168.6725 | I39: =SUM(I33:I38) -> 3480.2788 | J39: =SUM(J33:J38) -> 3788.9716 | K39: =SUM(K33:K38) -> 4217.6271 | L39: =SUM(L33:L38) -> 4527.4324
C41: (-) Tax Expense: | D41: ='3_Statment_model'!D135 -> $M | E41: =-E39*'3_Statment_model'!E21 -> -568.23818 | F41: =-F39*'3_Statment_model'!F21 -> -806.8716 | G41: =-G39*'3_Statment_model'!G21 -> -807.52941 | H41: =-H39*'3_Statment_model'!H21 -> -877.06122 | I41: =-I39*'3_Statment_model'!I21 -> -963.31116 | J41: =-J39*'3_Statment_model'!J21 -> -1048.7547 | K41: =-K39*'3_Statment_model'!K21 -> -1167.4028 | L41: =-L39*'3_Statment_model'!L21 -> -1253.1543
C42: Net Operating Profit After Taxes (NOPAT): | D42: ='3_Statment_model'!D136 -> $M | E42: =SUM(E39:E41) -> 1744.7618 | F42: =SUM(F39:F41) -> 1777.1284 | G42: =SUM(G39:G41) -> 2156.4706 | H42: =SUM(H39:H41) -> 2291.6113 | I42: =SUM(I39:I41) -> 2516.9676 | J42: =SUM(J39:J41) -> 2740.217 | K42: =SUM(K39:K41) -> 3050.2243 | L42: =SUM(L39:L41) -> 3274.2782
C44: (+) Depreciation and Amortisation: | D44: ='3_Statment_model'!D137 -> $M | E44: =SUM('3_Statment_model'!E191:E192) -> 1018 | F44: =SUM('3_Statment_model'!F191:F192) -> 1144 | G44: =SUM('3_Statment_model'!G191:G192) -> 1302 | H44: =SUM('3_Statment_model'!H191:H192) -> 1355.043 | I44: =SUM('3_Statment_model'!I191:I192) -> 1416.4544 | J44: =SUM('3_Statment_model'!J191:J192) -> 1490.9434 | K44: =SUM('3_Statment_model'!K191:K192) -> 1576.6617 | L44: =SUM('3_Statment_model'!L191:L192) -> 1672.5334
C45: (+/-) Change in Working Capital: | D45: ='3_Statment_model'!D138 -> $M | E45: ='3_Statment_model'!E194 -> -120 | F45: ='3_Statment_model'!F194 -> 186 | G45: ='3_Statment_model'!G194 -> -40 | H45: ='3_Statment_model'!H194 -> 40.169327 | I45: ='3_Statment_model'!I194 -> 101.37952 | J45: ='3_Statment_model'!J194 -> 92.823283 | K45: ='3_Statment_model'!K194 -> 94.711764 | L45: ='3_Statment_model'!L194 -> 157.53166
C46: (-) Net CapEx | D46: ='3_Statment_model'!D140 -> $M | E46: ='3_Statment_model'!E198 -> -1010 | F46: ='3_Statment_model'!F198 -> -1328 | G46: ='3_Statment_model'!G198 -> -1317 | H46: ='3_Statment_model'!H198 -> -1440.4019 | I46: ='3_Statment_model'!I198 -> -1574.72 | J46: ='3_Statment_model'!J198 -> -1712.6633 | K46: ='3_Statment_model'!K198 -> -1856.2799 | L46: ='3_Statment_model'!L198 -> -2005.0035
C48: Unlevered Free Cash Flow: | D48: ='3_Statment_model'!D142 -> $M | E48: =SUM(E42:E46) -> 1632.7618 | F48: =SUM(F42:F46) -> 1779.1284 | G48: =SUM(G42:G46) -> 2101.4706 | H48: =SUM(H42:H46) -> 2246.4217 | I48: =SUM(I42:I46) -> 2460.0816 | J48: =SUM(J42:J46) -> 2611.3204 | K48: =SUM(K42:K46) -> 2865.3178 | L48: =SUM(L42:L46) -> 3099.3397
B51: WACC Calculation:
C52: Risk-Free Rate (10 Year Govt Bond): | D52: 0.0488
C53: Equity Risk Premium: | D53: 0.0501
C54: Pre-Tax Cost of Debt: | D54: =(0.0385*337+0.0364*300+0.015*554+0.02*360+0.03*578+0.0325*889+0.0313*815+0.0438*314+0.0325*572)/4719 -> 0.030406802
C55: Cost of Preferred Stock: | D55: 0
C57: Unlevered Beta Calculations: | E57: Levered | H57: Preferred | J57: Equity | M57: Unlevered
C58: Name | D58: Ticker | E58: Beta | F58: Debt ($M) | G58: % Debt | H58: Stock ($M) | I58: % Preferred | J58: Value ($M) | K58: % Equity | L58: Tax Rate | M58: Beta
C59: Sodexo | D59: SW | E59: =Public_Comps!F12 -> 0.19 | F59: 5589 | G59: =F59/(F59+H59+J59) -> 0.36844881 | H59: 0 | I59: =H59/(F59+H59+J59) -> 0 | J59: =Public_Comps!E12 -> 9580 | K59: =J59/(F59+H59+J59) -> 0.63155119 | L59: =Public_Comps!G12 -> 0.259 | M59: =E59/(1+F59/J59*(1-L59)+H59/J59) -> 0.13265363
C60: Aramark | D60: ARMK | E60: =Public_Comps!F13 -> 1.18 | F60: 5349 | G60: =F60/(F60+H60+J60) -> 0.26312165 | H60: 0 | I60: =H60/(F60+H60+J60) -> 0 | J60: =Public_Comps!E13 -> 14980 | K60: =J60/(F60+H60+J60) -> 0.73687835 | L60: =Public_Comps!G13 -> 0.257 | M60: =E60/(1+F60/J60*(1-L60)+H60/J60) -> 0.9325796
C61: Elior Group | D61: ELIOR | E61: =Public_Comps!F14 -> 1.87 | F61: 1353 | G61: =F61/(F61+H61+J61) -> 0.68715084 | H61: 0 | I61: =H61/(F61+H61+J61) -> 0 | J61: =Public_Comps!E14 -> 616 | K61: =J61/(F61+H61+J61) -> 0.31284916 | L61: =Public_Comps!G14 -> 0.322 | M61: =E61/(1+F61/J61*(1-L61)+H61/J61) -> 0.75125185
C62: ISS Group | D62: ISS | E62: =Public_Comps!F15 -> 0.85 | F62: 2011 | G62: =F62/(F62+H62+J62) -> 0.22441692 | H62: 0 | I62: =H62/(F62+H62+J62) -> 0 | J62: =Public_Comps!E15 -> 6950 | K62: =J62/(F62+H62+J62) -> 0.77558308 | L62: =Public_Comps!G15 -> 0.206 | M62: =E62/(1+F62/J62*(1-L62)+H62/J62) -> 0.6911997
C63: SSP Group | D63: SSPG | E63: =Public_Comps!F16 -> 0.91 | F63: 916 | G63: =F63/(F63+H63+J63) -> 0.30987821 | H63: 0 | I63: =H63/(F63+H63+J63) -> 0 | J63: =Public_Comps!E16 -> 2040 | K63: =J63/(F63+H63+J63) -> 0.69012179 | L63: =Public_Comps!G16 -> 0.225 | M63: =E63/(1+F63/J63*(1-L63)+H63/J63) -> 0.67507909
C65: Median | E65: =MEDIAN(E59:E63) -> 0.91 | F65: =MEDIAN(F59:F63) -> 2011 | G65: =MEDIAN(G59:G63) -> 0.30987821 | H65: =MEDIAN(H59:H63) -> 0 | I65: =MEDIAN(I59:I63) -> 0 | J65: =MEDIAN(J59:J63) -> 6950 | K65: =MEDIAN(K59:K63) -> 0.69012179 | L65: =MEDIAN(L59:L63) -> 0.257 | M65: =MEDIAN(M59:M63) -> 0.6911997
C67: Levered Beta Calculations: | E67: Unlevered | H67: Preferred | J67: Equity | M67: Levered
D68: Ticker | E68: Beta | F68: Debt ($M) | G68: % Debt | H68: Stock ($M) | I68: % Preferred | J68: Value ($M) | K68: % Equity | L68: Tax Rate | M68: Beta
C69: Current Capital Structure: | D69: CPG | E69: =$M$65 -> 0.6911997 | F69: =-'3_Statment_model'!G165-'3_Statment_model'!G172 -> 5426 | G69: =F69/(F69+H69+J69) -> 0.08747613 | H69: 0 | I69: =H69/(F69+H69+J69) -> 0 | J69: =E13 -> 56602.35 | K69: =J69/(F69+H69+J69) -> 0.91252387 | L69: ='3_Statment_model'!$G$21 -> 0.27244582 | M69: =E69*(1+F69/J69*(1-L69)+H69/J69) -> 0.73940716
C70: Optimal Capital Structure: | D70: CPG | E70: =$M$65 -> 0.6911997 | F70: =(F69+H69+J69)*G70 -> 19221.234 | G70: =1-K70-I70 -> 0.30987821 | H70: 0 | I70: 0 | J70: =(J69+H69+F69)*K70 -> 42807.116 | K70: =K65 -> 0.69012179 | L70: ='3_Statment_model'!$G$21 -> 0.27244582 | M70: =E70*(1+F70/J70*(1-L70)+H70/J70) -> 0.91700503
C72: Cost of Equity Based on Historical Beta: | F72: =D52+D53*Public_Comps!F24 -> 0.081365
C73: Cost of Equity Based on Comparables Using Current Capital Structure: | F73: =$D$52+$D$53*M69 -> 0.085844299
C74: Cost of Equity Based on Comparables Using Optimal Capital Structure: | F74: =$D$52+$D$53*M70 -> 0.094741952
C76: WACC (Historical Cost of Equity): | F76: =$D$54*(1-$L$69)*G69+F72*K69+D55*I69 -> 0.076182704
C77: WACC (Current Capital Structure): | F77: =$D$54*(1-$L$69)*G69+F73*K69+D55*H69 -> 0.080270171
C78: WACC (Optimal Capital Structure): | F78: =$D$54*(1-$L$70)*G70+F74*K70+D55*H70 -> 0.072238796
B80: Sensitivity Analysis:
D82: Discount Rate (WACC):
D83: =J28 -> 28.294218 | E83: 0.07 | F83: =E83+0.0025 -> 0.0725 | G83: =F83+0.0025 -> 0.075 | H83: =G83+0.0025 -> 0.0775 | I83: =H83+0.0025 -> 0.08 | J83: =I83+0.0025 -> 0.0825 | K83: =J83+0.0025 -> 0.085 | L83: =K83+0.0025 -> 0.0875 | M83: =L83+0.0025 -> 0.09 | ... O83: =N83+0.0025 -> 0.095
D84: 12 | E84: 32.212554 | F84: 31.825387 | G84: 31.44347 | H84: 31.066717 | I84: 30.695046 | J84: 30.328377 | K84: 29.966631 | L84: 29.609729 | M84: 29.257595 | N84: 28.910154 | O84: 28.567333
D85: =D84-0.25 -> 11.75 | E85: 31.593437 | F85: 31.213453 | G85: 30.838618 | H85: 30.468849 | I85: 30.104067 | J85: 29.744191 | K85: 29.389144 | L85: 29.038849 | M85: 28.693232 | N85: 28.352219 | O85: 28.015738
D86: =D85-0.25 -> 11.5 | E86: 30.974321 | F86: 30.601519 | G86: 30.233767 | H86: 29.870982 | I86: 29.513087 | J86: 29.160004 | K86: 28.811656 | L86: 28.467969 | M86: 28.128869 | N86: 27.794284 | O86: 27.464143
D87: =D86-0.25 -> 11.25 | E87: 30.355205 | F87: 29.989585 | G87: 29.628915 | H87: 29.273115 | I87: 28.922108 | J87: 28.575818 | K87: 28.234169 | L87: 27.897089 | M87: 27.564506 | N87: 27.236348 | O87: 26.912547
C88: Terminal TEV / EBITDA Multiple: | D88: =D87-0.25 -> 11 | E88: 29.736089 | F88: 29.377651 | G88: 29.024064 | H88: 28.675248 | I88: 28.331129 | J88: 27.991631 | K88: 27.656682 | L88: 27.326209 | M88: 27.000143 | N88: 26.678413 | O88: 26.360952
D89: =D88-0.25 -> 10.75 | E89: 29.116972 | F89: 28.765717 | G89: 28.419212 | H89: 28.077381 | I89: 27.740149 | J89: 27.407444 | K89: 27.079195 | L89: 26.755329 | M89: 26.43578 | N89: 26.120478 | O89: 25.809357
D90: =D89-0.25 -> 10.5 | E90: 28.497856 | F90: 28.153783 | G90: 27.814361 | H90: 27.479514 | I90: 27.14917 | J90: 26.823258 | K90: 26.501707 | L90: 26.184449 | M90: 25.871417 | N90: 25.562542 | O90: 25.257762
D91: =D90-0.25 -> 10.25 | E91: 27.87874 | F91: 27.541849 | G91: 27.209509 | H91: 26.881647 | I91: 26.558191 | J91: 26.239071 | K91: 25.92422 | L91: 25.61357 | M91: 25.307054 | N91: 25.004607 | O91: 24.706167
D92: =D91-0.25 -> 10 | E92: 27.259624 | F92: 26.929915 | G92: 26.604658 | H92: 26.283779 | I92: 25.967211 | J92: 25.654885 | K92: 25.346733 | L92: 25.04269 | M92: 24.742691 | N92: 24.446672 | O92: 24.154571
D93: =D92-0.25 -> 9.75 | E93: 26.640507 | F93: 26.317981 | G93: 25.999806 | H93: 25.685912 | I93: 25.376232 | J93: 25.070698 | K93: 24.769246 | L93: 24.47181 | M93: 24.178327 | N93: 23.888737 | O93: 23.602976
D94: =D93-0.25 -> 9.5 | E94: 26.021391 | F94: 25.706047 | G94: 25.394955 | H94: 25.088045 | I94: 24.785253 | J94: 24.486512 | K94: 24.191758 | L94: 23.90093 | M94: 23.613964 | N94: 23.330801 | O94: 23.051381
D97: Discount Rate (WACC):
D98: =O28 -> 26.505832 | E98: 0.07 | F98: =E98+0.0025 -> 0.0725 | G98: =F98+0.0025 -> 0.075 | H98: =G98+0.0025 -> 0.0775 | I98: =H98+0.0025 -> 0.08 | J98: =I98+0.0025 -> 0.0825 | K98: =J98+0.0025 -> 0.085 | L98: =K98+0.0025 -> 0.0875 | M98: =L98+0.0025 -> 0.09 | ... O98: =N98+0.0025 -> 0.095
D99: 0.035 | E99: 39.10368 | F99: 36.224303 | G99: 33.705168 | H99: 31.482698 | I99: 29.507447 | J99: 27.740375 | K99: 26.150254 | L99: 24.711802 | M99: 23.404334 | N99: 22.210763 | O99: 21.116849
D100: =D99-0.0015 -> 0.0335 | E100: 37.548337 | F100: 34.878328 | G100: 32.530324 | H100: 30.449434 | I100: 28.592572 | J100: 26.925444 | K100: 25.420417 | L100: 24.054973 | M100: 22.810582 | N100: 21.671852 | O100: 20.625897
D101: =D100-0.001 -> 0.0325 | E101: 36.580568 | F101: 34.037093 | G101: 31.793167 | H101: 29.79886 | I101: 28.014756 | J101: 26.409321 | K101: 24.957028 | L101: 23.636992 | M101: 22.431958 | N101: 21.327549 | O101: 20.311687
D102: =D101-0.001 -> 0.0315 | E102: 35.663072 | F102: 33.236894 | G102: 31.089902 | H102: 29.176572 | I102: 27.460768 | J102: 25.913438 | K102: 24.510962 | L102: 23.233938 | M102: 22.066278 | N102: 20.994533 | O102: 20.007374
C103: Terminal FCF Growth Rate: | D103: =D102-0.001 -> 0.0305 | E103: 34.792033 | F103: 32.4748 | G103: 30.418244 | H103: 28.580764 | I103: 26.929163 | J103: 25.436628 | K103: 24.081266 | L103: 22.845026 | M103: 21.712889 | N103: 20.672261 | O103: 19.712497
D104: =D103-0.001 -> 0.0295 | E104: 33.964007 | F104: 31.748152 | G104: 29.77611 | H104: 28.009782 | I104: 26.418611 | J104: 24.97781 | K104: 23.667054 | L104: 22.469525 | M104: 21.371183 | N104: 20.360219 | O104: 19.426624
D105: =D104-0.001 -> 0.0285 | E105: 33.175886 | F105: 31.054534 | G105: 29.161595 | H105: 27.462105 | I105: 25.927887 | J105: 24.535986 | K105: 23.267505 | L105: 22.106753 | M105: 21.04059 | N105: 20.057928 | O105: 19.149348
D106: =D105-0.001 -> 0.0275 | E106: 32.424854 | F106: 30.391743 | G106: 28.572954 | H106: 26.936335 | I106: 25.455858 | J106: 24.110228 | K106: 22.881853 | L106: 21.756073 | M106: 20.720575 | N106: 19.764939 | O106: 18.880288
D107: =D106-0.001 -> 0.0265 | E107: 31.708351 | F107: 29.757769 | G107: 28.008587 | H107: 26.431183 | I107: 25.001474 | J107: 23.699675 | K107: 22.509385 | L107: 21.416891 | M107: 20.41064 | N107: 19.480828 | O107: 18.619084
D108: =D107-0.001 -> 0.0255 | E108: 31.024051 | F108: 29.150773 | G108: 27.467022 | H108: 25.945461 | I108: 24.563765 | J108: 23.303528 | K108: 22.149438 | L108: 21.08865 | M108: 20.110315 | N108: 19.205198 | O108: 18.365396
D109: =D108-0.001 -> 0.0245 | E109: 30.36983 | F109: 28.569068 | G109: 26.946906 | H109: 25.478067 | I109: 24.141829 | J109: 22.921041 | K109: 21.801389 | L109: 20.77083 | M109: 19.81916 | N109: 18.937675 | O109: 18.118906

Sheet 3_Statment_model
C2: Company Name: | E2: =Valuation_Summary!E2 -> Compass Group
C3: Last Historical Year: | E3: =Valuation_Summary!E5 -> 45930
F5: Historical: | J5: Projected:
B6: Financial Statement Drivers: | D6: Units: | E6: =EOMONTH(F6,-12) -> 45199 | F6: =EOMONTH(G6,-12) -> 45565 | G6: =$E$3 -> 45930 | H6: =EOMONTH(G6,12) -> 46295 | I6: =EOMONTH(H6,12) -> 46660 | J6: =EOMONTH(I6,12) -> 47026 | K6: =EOMONTH(J6,12) -> 47391 | L6: =EOMONTH(K6,12) -> 47756
B7: Income Statement Drivers:
C8: Revenue: | D8: $M | E8: 37907 | F8: 42002 | G8: 46070 | H8: =G8*(1+H9) -> 49755.6 | I8: =H8*(1+I9) -> 53561.903 | J8: =I8*(1+J9) -> 57471.922 | K8: =J8*(1+K9) -> 61466.221 | L8: =K8*(1+L9) -> 65522.992
C9: Revenue Growth Rate: | D9: % | F9: =(F8-E8)/E8 -> 0.10802754 | G9: =(G8-F8)/F8 -> 0.096852531 | H9: =SUM(H10:H12) -> 0.08 | I9: =SUM(I10:I12) -> 0.0765 | J9: =SUM(J10:J12) -> 0.073 | K9: =SUM(K10:K12) -> 0.0695 | L9: =SUM(L10:L12) -> 0.066
C10: Net New Business Growth: | D10: % | H10: 0.045 | I10: 0.0425 | J10: 0.04 | K10: 0.0375 | L10: 0.035
C11: Like-For-Like Growth: | D11: % | H11: 0.015 | I11: 0.014 | J11: 0.013 | K11: 0.012 | L11: 0.011
C12: Inflation: | D12: % | H12: 0.02 | I12: 0.02 | J12: 0.02 | K12: 0.02 | L12: 0.02
C14: Direct Costs: | D14: $M | E14: 12254 | F14: 13293 | G14: 14212 | H14: =H15*H8 -> 15225.214 | I14: =I15*I8 -> 16282.819 | J14: =J15*J8 -> 17356.521 | K14: =K15*K8 -> 18439.866 | L14: =L15*L8 -> 19656.897
C15: Direct Costs % Revenue: | D15: % | E15: =E14/E8 -> 0.32326483 | F15: =F14/F8 -> 0.31648493 | G15: =G14/G8 -> 0.30848708 | H15: 0.306 | I15: 0.304 | J15: 0.302 | K15: 0.3 | L15: 0.3
C16: SG&A: | D16: $M | E16: 22175 | F16: 24711 | G16: 27373 | H16: =H17*H8 -> 29654.338 | I16: =I17*I8 -> 32030.018 | J16: =J17*J8 -> 34483.153 | K16: =K17*K8 -> 36879.733 | L16: =L17*L8 -> 39313.795
C17: SG&A % Revenue: | D17: % | E17: =E16/E8 -> 0.5849843 | F17: =F16/F8 -> 0.58832913 | G17: =G16/G8 -> 0.59416106 | H17: 0.596 | I17: 0.598 | J17: 0.6 | K17: 0.6 | L17: 0.6
C18: Restructuring / Integration: | D18: $M | E18: 281 | F18: 408 | G18: 368 | H18: =AVERAGE(E18:G18) -> 352.33333 | I18: =H18 -> 352.33333 | J18: =I18 -> 352.33333 | K18: =J18 -> 352.33333 | L18: =K18 -> 352.33333
C20: Income Tax: | D20: $M | E20: 525 | F20: 642 | G20: 704 | H20: =MAX(0,H21*H138) -> 813.48766 | I20: =MAX(0,I21*I138) -> 901.93081 | J20: =MAX(0,J21*J138) -> 989.72115 | K20: =MAX(0,K21*K138) -> 1110.473 | L20: =MAX(0,L21*L138) -> 1198.2939
C21: Income Tax %: | D21: % | E21: =E20/E138 -> 0.2456715 | F21: =F20/F138 -> 0.31225681 | G21: =G20/G138 -> 0.27244582 | H21: =AVERAGE(E21:G21) -> 0.27679138 | I21: =H21 -> 0.27679138 | J21: =I21 -> 0.27679138 | K21: =J21 -> 0.27679138 | L21: =K21 -> 0.27679138
B23: Balance Sheet Drivers: | D23: =EOMONTH(E23,-12) -> 44834 | E23: =EOMONTH(F23,-12) -> 45199 | F23: =EOMONTH(G23,-12) -> 45565 | G23: =E3 -> 45930 | H23: =EOMONTH(G23,12) -> 46295 | I23: =EOMONTH(H23,12) -> 46660 | J23: =EOMONTH(I23,12) -> 47026 | K23: =EOMONTH(J23,12) -> 47391 | L23: =EOMONTH(K23,12) -> 47756
C24: Days Sales Outstanding (DSO): | D24: # Days | E24: =(E157/E127)*(E23-D23) -> 49.049252 | F24: =(F157/F127)*(F23-E23) -> 49.547069 | G24: =(G157/G127)*(G23-F23) -> 50.309312 | H24: =AVERAGE(E24:G24) -> 49.635211 | I24: =H24 -> 49.635211 | J24: =I24 -> 49.635211 | K24: =J24 -> 49.635211 | L24: =K24 -> 49.635211
C25: Days Inventory Outstanding (DIO): | D25: # Days | E25: =-(E156/E128)*(E23-D23) -> 20.612045 | F25: =-(F156/F128)*(F23-E23) -> 20.209434 | G25: =-(G156/G128)*(G23-F23) -> 21.059668 | H25: =AVERAGE(E25:G25) -> 20.627049 | I25: =H25 -> 20.627049 | J25: =I25 -> 20.627049 | K25: =J25 -> 20.627049 | L25: =K25 -> 20.627049
C26: Days Payable Outstanding (DPO): | D26: # Days | E26: =(E167/E128)*(E23-D23) -> 213.44785 | F26: =(F167/F128)*(F23-E23) -> 225.00203 | G26: =(G167/G128)*(G23-F23) -> 221.87131 | H26: =AVERAGE(E26:G26) -> 220.10706 | I26: =H26 -> 220.10706 | J26: =I26 -> 220.10706 | K26: =J26 -> 220.10706 | L26: =K26 -> 220.10706
C28: Other Current Assets % Revenue: | D28: % | E28: =E159/E127 -> 0.0035877279 | F28: =F159/F127 -> 0.010713776 | G28: =G159/G127 -> 0.0010418928 | H28: =AVERAGE(E28:G28) -> 0.0051144654 | I28: =H28 -> 0.0051144654 | J28: =I28 -> 0.0051144654 | K28: =J28 -> 0.0051144654 | L28: =K28 -> 0.0051144654
C29: Other Current Liabilities % Total Expenses: | D29: % | E29: =E168/SUM(E128:E131) -> 0.016544221 | F29: =F168/SUM(F128:F131) -> 0.020399372 | G29: =G168/SUM(G128:G131) -> 0.014950282 | H29: =AVERAGE(E29:G29) -> 0.017297958 | I29: =H29 -> 0.017297958 | J29: =I29 -> 0.017297958 | K29: =J29 -> 0.017297958 | L29: =K29 -> 0.017297958
C31: Other Long-Term Liabilities % Total Expenses: | D31: % | E31: =E174/SUM(E128:E131) -> 0.060568673 | F31: =F174/SUM(F128:F131) -> 0.064745831 | G31: =G174/SUM(G128:G131) -> 0.062095821 | H31: =AVERAGE(E31:G31) -> 0.062470108 | I31: =H31 -> 0.062470108 | J31: =I31 -> 0.062470108 | K31: =J31 -> 0.062470108 | L31: =K31 -> 0.062470108
C32: Other Long-Term Assets Growth Rate: | D32: % | F32: =(F152-E152)/E152 -> 0.031945006 | G32: =(G152-F152)/F152 -> 0.028605016 | H32: 0.027 | I32: 0.026 | J32: 0.025 | K32: 0.025 | L32: 0.025
B34: Cash Flow Statement Drivers:
C35: Dividends: | D35: $M | E35: 803 | F35: 973 | G35: 1055 | H35: =H36*H142 -> 1169.0274 | I35: =I36*I142 -> 1296.1252 | J35: =J36*J142 -> 1422.2848 | K35: =K36*K142 -> 1595.812 | L35: =L36*L142 -> 1722.0155
C36: Dividend Payout Ratio: | D36: % | E36: =E35/E190 -> 0.49813896 | F36: =F35/F190 -> 0.68811881 | G36: =G35/G190 -> 0.56117021 | H36: 0.55 | I36: 0.55 | J36: 0.55 | K36: 0.55 | L36: 0.55
C38: Stock Repurchases: | D38: $M | E38: 1167 | F38: 577 | G38: 115 | H38: =H39*H142 -> 531.3761 | I38: =I39*I142 -> 589.14781 | J38: =J39*J142 -> 646.49311 | K38: =K39*K142 -> 725.3691 | L38: =L39*L142 -> 782.73434
C39: Stock Repurchases % Net Income: | D39: % | E39: =E38/E142 -> 0.72394541 | F39: =F38/F142 -> 0.40806223 | G39: =G38/G142 -> 0.061170213 | H39: 0.25 | I39: 0.25 | J39: 0.25 | K39: 0.25 | L39: 0.25
B41: Debt Schedule:
C42: Interest Rates:
C43: Short-Term Borrowings: | D43: % | E43: 0.0412
C44: Bond Maturing in Forecast (FY26 - FY30): | D44: % | E44: 0.0244
C45: Long-Dated Bonds (Maturing After FY30): | D45: % | E45: 0.0335
C47: Short-Term Borrowings (Commercial Paper + Overdraft):
C48: Beginning Balance: | D48: $M | H48: 1043 | I48: =H51 -> 1043 | J48: =I51 -> 1043 | K48: =J51 -> 1043 | L48: =K51 -> 1043
C49: (-) Repayments: | D49: $M | H49: -337 | I49: 0 | J49: 0 | K49: 0 | L49: 0
C50: (+) Issuances: | D50: $M | H50: =-H49 -> 337 | I50: =-I49 -> 0 | J50: =-J49 -> 0 | K50: =-K49 -> 0 | L50: =-L49 -> 0
C51: Ending Balance: | D51: $M | H51: =SUM(H48:H50) -> 1043 | I51: =SUM(I48:I50) -> 1043 | J51: =SUM(J48:J50) -> 1043 | K51: =SUM(K48:K50) -> 1043 | L51: =SUM(L48:L50) -> 1043
C53: Bonds Maturing in Forecast (FY26 - FY30):
C54: Beginning Balance: | D54: $M | H54: 1792 | I54: =H57 -> 1792 | J54: =I57 -> 1792 | K54: =J57 -> 1792 | L54: =K57 -> 1792
C55: (-) Repayments: | D55: $M | H55: 0 | I55: -300 | J55: -554 | K55: -360 | L55: -578
C56: (+) Issuances: | D56: $M | H56: =-H55 -> 0 | I56: =-I55 -> 300 | J56: =-J55 -> 554 | K56: =-K55 -> 360 | L56: =-L55 -> 578
C57: Ending Balance: | D57: $M | H57: =SUM(H54:H56) -> 1792 | I57: =SUM(I54:I56) -> 1792 | J57: =SUM(J54:J56) -> 1792 | K57: =SUM(K54:K56) -> 1792 | L57: =SUM(L54:L56) -> 1792
C59: Long-Dated Bonds (Maturing After FY30):
C60: Beginning Balance: | D60: $M | H60: 2591 | I60: =H63 -> 2591 | J60: =I63 -> 2591 | K60: =J63 -> 2591 | L60: =K63 -> 2591
C61: (-) Repayments: | D61: $M | H61: 0 | I61: 0 | J61: 0 | K61: 0 | L61: 0
C62: (+) Issuances: | D62: $M | H62: =-H61 -> 0 | I62: =-I61 -> 0 | J62: =-J61 -> 0 | K62: =-K61 -> 0 | L62: =-L61 -> 0
C63: Ending Balance: | D63: $M | H63: =SUM(H60:H62) -> 2591 | I63: =SUM(I60:I62) -> 2591 | J63: =SUM(J60:J62) -> 2591 | K63: =SUM(K60:K62) -> 2591 | L63: =SUM(L60:L62) -> 2591
C65: Interest Expense for Short-Term Borrowings: | D65: $M | H65: =AVERAGE(H48,H51)*$E$43 -> 42.9716 | I65: =AVERAGE(I48,I51)*$E$43 -> 42.9716 | J65: =AVERAGE(J48,J51)*$E$43 -> 42.9716 | K65: =AVERAGE(K48,K51)*$E$43 -> 42.9716 | L65: =AVERAGE(L48,L51)*$E$43 -> 42.9716
C66: Interest Expense for Bonds Maturing in Forecast (FY26 - FY30): | D66: $M | H66: =AVERAGE(H54,H57)*$E$44 -> 43.7248 | I66: =AVERAGE(I54,I57)*$E$44 -> 43.7248 | J66: =AVERAGE(J54,J57)*$E$44 -> 43.7248 | K66: =AVERAGE(K54,K57)*$E$44 -> 43.7248 | L66: =AVERAGE(L54,L57)*$E$44 -> 43.7248
C67: Interest Expense for Bonds (Maturing After FY30); | D67: $M | H67: =AVERAGE(H60,H63)*$E$45 -> 86.7985 | I67: =AVERAGE(I60,I63)*$E$45 -> 86.7985 | J67: =AVERAGE(J60,J63)*$E$45 -> 86.7985 | K67: =AVERAGE(K60,K63)*$E$45 -> 86.7985 | L67: =AVERAGE(L60,L63)*$E$45 -> 86.7985
C68: Total Interest Expense: | D68: $M | H68: =SUM(H65:H67) -> 173.4949 | I68: =SUM(I65:I67) -> 173.4949 | J68: =SUM(J65:J67) -> 173.4949 | K68: =SUM(K65:K67) -> 173.4949 | L68: =SUM(L65:L67) -> 173.4949
C70: Money Market Rate: | D70: % | E70: 0.035
B72: CapEx and Depreciation:
C73: CapEx on PP&E: | D73: $M | E73: =445-78 -> 367 | F73: =572-81 -> 491 | G73: =545-67 -> 478 | H73: =H74*H127 -> 526.53075 | I73: =I74*I127 -> 578.46856 | J73: =J74*J127 -> 632.19115 | K73: =K74*K127 -> 688.42167 | L73: =L74*L127 -> 746.9621
C74: CapEx on PP&E % Revenue: | D74: % | E74: =E73/E127 -> 0.0096815892 | F74: =F73/F127 -> 0.01168992 | G74: =G73/G127 -> 0.010375516 | H74: =AVERAGE(E74:G74) -> 0.010582341 | I74: 0.0108 | J74: 0.011 | K74: 0.0112 | L74: 0.0114
C75: Spending on Intangibles: | D75: $M | E75: =263+380 -> 643 | F75: =329+508 -> 837 | G75: =347+492 -> 839 | H75: =H76*H127 -> 913.87116 | I75: =I76*I127 -> 996.2514 | J75: =J76*J127 -> 1080.4721 | K75: =K76*K127 -> 1167.8582 | L75: =L76*L127 -> 1258.0414
C76: Spending on Intangibles % Revenue: | D76: % | E76: =E75/E127 -> 0.016962566 | F76: =F75/F127 -> 0.019927622 | G76: =G75/G127 -> 0.018211417 | H76: =AVERAGE(E76:G76) -> 0.018367202 | I76: 0.0186 | J76: 0.0188 | K76: 0.019 | L76: 0.0192
C77: Net CapEx: | D77: $M | E77: =E73+E75 -> 1010 | F77: =F73+F75 -> 1328 | G77: =G73+G75 -> 1317 | H77: =H73+H75 -> 1440.4019 | I77: =I73+I75 -> 1574.72 | J77: =J73+J75 -> 1712.6633 | K77: =K73+K75 -> 1856.2799 | L77: =L73+L75 -> 2005.0035
C79: Depreciation of PP&E: | D79: $M | E79: 337 | F79: 374 | G79: 407 | H79: =H80*H84 -> 425.45183 | I79: =I80*I84 -> 452.86051 | J79: =J80*J84 -> 486.92053 | K79: =K80*K84 -> 526.31228 | L79: =L80*L84 -> 570.27005
C80: Depreciation of PP&E % PP&E: | D80: % | E80: =E79/E87 -> 0.2890223 | F80: =F79/F87 -> 0.26506024 | G80: =G79/G87 -> 0.25940089 | H80: =AVERAGE(E80:G80) -> 0.27116114 | I80: =H80 -> 0.27116114 | J80: =I80 -> 0.27116114 | K80: =J80 -> 0.27116114 | L80: =K80 -> 0.27116114
C81: Amortisation of Intangibles: | D81: $M | E81: =134+282+66 -> 482 | F81: =150+306+94 -> 550 | G81: =183+338+112 -> 633 | H81: =H82*H89 -> 664.83334 | I81: =I82*I89 -> 694.06509 | J81: =J82*J89 -> 729.53534 | K81: =K82*K89 -> 770.72787 | L81: =L82*L89 -> 817.34254
C82: Amortisation of Intangibles % Intangibles: | D82: % | E82: =E81/E92 -> 0.12697576 | F82: =F81/F92 -> 0.11340206 | G82: =G81/G92 -> 0.11175847 | H82: =AVERAGE(E82:G82) -> 0.11737877 | I82: =H82 -> 0.11737877 | J82: =I82 -> 0.11737877 | K82: =J82 -> 0.11737877 | L82: =K82 -> 0.11737877
C84: Beginning PP&E: | D84: $M | H84: 1569 | I84: =H87 -> 1670.0789 | J84: =I87 -> 1795.687 | K84: =J87 -> 1940.9576 | L84: =K87 -> 2103.067
C85: (+) CapEx on PP&E: | D85: $M | H85: =H73 -> 526.53075 | I85: =I73 -> 578.46856 | J85: =J73 -> 632.19115 | K85: =K73 -> 688.42167 | L85: =L73 -> 746.9621
C86: (-) Depreciation of PP&E: | D86: $M | H86: =-H79 -> -425.45183 | I86: =-I79 -> -452.86051 | J86: =-J79 -> -486.92053 | K86: =-K79 -> -526.31228 | L86: =-L79 -> -570.27005
C87: Closing PP&E: | D87: $M | E87: 1166 | F87: 1411 | G87: 1569 | H87: =SUM(H84:H86) -> 1670.0789 | I87: =SUM(I84:I86) -> 1795.687 | J87: =SUM(J84:J86) -> 1940.9576 | K87: =SUM(K84:K86) -> 2103.067 | L87: =SUM(L84:L86) -> 2279.759
C89: Beginning Intangibles: | D89: $M | H89: 5664 | I89: =H92 -> 5913.0378 | J89: =I92 -> 6215.2241 | K89: =J92 -> 6566.1609 | L89: =K92 -> 6963.2913
C90: (+) Spending on Intangibles: | D90: $M | H90: =H75 -> 913.87116 | I90: =I75 -> 996.2514 | J90: =J75 -> 1080.4721 | K90: =K75 -> 1167.8582 | L90: =L75 -> 1258.0414
C91: (-) Amortisation of Intangibles: | D91: $M | H91: =-H81 -> -664.83334 | I91: =-I81 -> -694.06509 | J91: =-J81 -> -729.53534 | K91: =-K81 -> -770.72787 | L91: =-L81 -> -817.34254
C92: Closing Intangibles: | D92: $M | E92: =2480+1316 -> 3796 | F92: =3325+1525 -> 4850 | G92: =3999+1665 -> 5664 | H92: =SUM(H89:H91) -> 5913.0378 | I92: =SUM(I89:I91) -> 6215.2241 | J92: =SUM(J89:J91) -> 6566.1609 | K92: =SUM(K89:K91) -> 6963.2913 | L92: =SUM(L89:L91) -> 7403.9902
B94: Lease Cycle:
C95: ROU Assets: | D95: $M | E95: 992 | F95: 1144 | G95: 1377 | H95: =H118 -> 1416.2422 | I95: =I118 -> 1456.7934 | J95: =J118 -> 1498.5874 | K95: =K118 -> 1541.5732 | L95: =L118 -> 1585.7117
C97: Short-Term Lease Liability: | D97: $M | E97: 237 | F97: 273 | G97: 338 | H97: =H100*H98 -> 334.2504 | I97: =I100*I98 -> 340.39988 | J97: =J100*J98 -> 346.76665 | K97: =K100*K98 -> 353.33846 | L97: =L100*L98 -> 360.10572
C98: Short-Term Lease Liability % Total Lease Liability: | D98: % | E98: =E97/E100 -> 0.20555074 | F98: =F97/F100 -> 0.20760456 | G98: =G97/G100 -> 0.21583653 | H98: =AVERAGE(E98:G98) -> 0.20966394 | I98: =H98 -> 0.20966394 | J98: =I98 -> 0.20966394 | K98: =J98 -> 0.20966394 | L98: =K98 -> 0.20966394
C99: Long-Term Lease Liability: | D99: $M | E99: 916 | F99: 1042 | G99: 1228 | H99: =H100-H97 -> 1259.9694 | I99: =I100-I97 -> 1283.15 | J99: =J100-J97 -> 1307.1498 | K99: =K100-K97 -> 1331.9225 | L99: =L100-L97 -> 1357.432
C100: Total Lease Liability: | D100: $M | E100: =E97+E99 -> 1153 | F100: =F97+F99 -> 1315 | G100: =G97+G99 -> 1566 | H100: =H123 -> 1594.2198 | I100: =I123 -> 1623.5499 | J100: =J123 -> 1653.9165 | K100: =K123 -> 1685.261 | L100: =L123 -> 1717.5377
C102: Additions: | D102: $M | E102: 280 | F102: 262 | G102: 370 | H102: =AVERAGE(E102:G102) -> 304 | I102: =H102*(1+I103) -> 310.08 | J102: =I102*(1+J103) -> 316.2816 | K102: =J102*(1+K103) -> 322.60723 | L102: =K102*(1+L103) -> 329.05938
C103: Additions Growth Rate: | D103: % | I103: 0.02 | J103: 0.02 | K103: 0.02 | L103: 0.02
C105: Lease Interest Expense: | D105: $M | E105: 50 | F105: 65 | G105: 77 | H105: =H106*G100 -> 74.105548 | I105: =I106*H100 -> 75.440952 | J105: =J106*I100 -> 76.8289 | K105: =K106*J100 -> 78.265892 | L105: =L106*K100 -> 79.749162
C106: Lease Interest Expense % Lease Liability: | D106: % | E106: =E105/E100 -> 0.043365134 | F106: =F105/F100 -> 0.049429658 | G106: =G105/G100 -> 0.04916986 | H106: =AVERAGE(E106:G106) -> 0.047321551 | I106: =H106 -> 0.047321551 | J106: =I106 -> 0.047321551 | K106: =J106 -> 0.047321551 | L106: =K106 -> 0.047321551
C107: Lease Depreciation: | D107: $M | E107: 199 | F107: 220 | G107: 262 | H107: =H108*G100 -> 264.7578 | I107: =I108*H100 -> 269.52881 | J107: =J108*I100 -> 274.48755 | K107: =K108*J100 -> 279.62151 | L107: =L108*K100 -> 284.92081
C108: Lease Depreciation % Lease Liability: | D108: % | E108: =E107/E100 -> 0.17259324 | F108: =F107/F100 -> 0.16730038 | G108: =G107/G100 -> 0.16730524 | H108: =AVERAGE(E108:G108) -> 0.16906628 | I108: =H108 -> 0.16906628 | J108: =I108 -> 0.16906628 | K108: =J108 -> 0.16906628 | L108: =K108 -> 0.16906628
C110: Total Cash Lease Payment: | D110: $M | E110: =E113+E105 -> 265 | F110: =F113+F105 -> 292 | G110: =G113+G105 -> 342 | H110: =H111*G100 -> 349.88577 | I110: =I111*H100 -> 356.19081 | J110: =J111*I100 -> 362.74394 | K110: =K111*J100 -> 369.52863 | L110: =L111*K100 -> 376.53182
C111: Total Cash Lease Payment % Lease Liability: | D111: % | E111: =E110/E100 -> 0.22983521 | F111: =F110/F100 -> 0.22205323 | G111: =G110/G100 -> 0.2183908 | H111: =AVERAGE(E111:G111) -> 0.22342642 | I111: =H111 -> 0.22342642 | J111: =I111 -> 0.22342642 | K111: =J111 -> 0.22342642 | L111: =K111 -> 0.22342642
C113: Lease Principal Repayment: | D113: $M | E113: 215 | F113: 227 | G113: 265 | H113: =H110-H105 -> 275.78022 | I113: =I110-I105 -> 280.74986 | J113: =J110-J105 -> 285.91504 | K113: =K110-K105 -> 291.26274 | L113: =L110-L105 -> 296.78266
C115: Beginning Rou Asset: | D115: $M | H115: =G95 -> 1377 | I115: =H118 -> 1416.2422 | J115: =I118 -> 1456.7934 | K115: =J118 -> 1498.5874 | L115: =K118 -> 1541.5732
C116: (+) New Leases: | D116: $M | H116: =H102 -> 304 | I116: =I102 -> 310.08 | J116: =J102 -> 316.2816 | K116: =K102 -> 322.60723 | L116: =L102 -> 329.05938
C117: (-) Lease Depreciation: | D117: $M | H117: =-H107 -> -264.7578 | I117: =-I107 -> -269.52881 | J117: =-J107 -> -274.48755 | K117: =-K107 -> -279.62151 | L117: =-L107 -> -284.92081
C118: Ending Rou Asset: | D118: $M | H118: =SUM(H115:H117) -> 1416.2422 | I118: =SUM(I115:I117) -> 1456.7934 | J118: =SUM(J115:J117) -> 1498.5874 | K118: =SUM(K115:K117) -> 1541.5732 | L118: =SUM(L115:L117) -> 1585.7117
C120: Beginning Lease Liability: | D120: $M | H120: =G100 -> 1566 | I120: =H123 -> 1594.2198 | J120: =I123 -> 1623.5499 | K120: =J123 -> 1653.9165 | L120: =K123 -> 1685.261
C121: (+) New Leases: | D121: $M | H121: =H102 -> 304 | I121: =I102 -> 310.08 | J121: =J102 -> 316.2816 | K121: =K102 -> 322.60723 | L121: =L102 -> 329.05938
C122: (-) Lease Principal Repayment: | D122: $M | H122: =-H113 -> -275.78022 | I122: =-I113 -> -280.74986 | J122: =-J113 -> -285.91504 | K122: =-K113 -> -291.26274 | L122: =-L113 -> -296.78266
C123: Ending Lease Liability: | D123: $M | H123: =SUM(H120:H122) -> 1594.2198 | I123: =SUM(I120:I122) -> 1623.5499 | J123: =SUM(J120:J122) -> 1653.9165 | K123: =SUM(K120:K122) -> 1685.261 | L123: =SUM(L120:L122) -> 1717.5377
F125: Historical: | J125: Projected:
B126: Income Statement: | D126: Units: | E126: =EOMONTH(F126,-12) -> 45199 | F126: =EOMONTH(G126,-12) -> 45565 | G126: =$E$3 -> 45930 | H126: =EOMONTH(G126,12) -> 46295 | I126: =EOMONTH(H126,12) -> 46660 | J126: =EOMONTH(I126,12) -> 47026 | K126: =EOMONTH(J126,12) -> 47391 | L126: =EOMONTH(K126,12) -> 47756
C127: Revenue: | D127: $M | E127: 37907 | F127: 42002 | G127: 46070 | H127: =H8 -> 49755.6 | I127: =I8 -> 53561.903 | J127: =J8 -> 57471.922 | K127: =K8 -> 61466.221 | L127: =L8 -> 65522.992
C128: (-) Direct Costs: | D128: $M | E128: -12254 | F128: -13293 | G128: -14212 | H128: =-H14 -> -15225.214 | I128: =-I14 -> -16282.819 | J128: =-J14 -> -17356.521 | K128: =-K14 -> -18439.866 | L128: =-L14 -> -19656.897
...

Sheet Public_Comps
B9: Operating Statistics: | R9: Projected | S9: Projected
D10: Share | E10: Equity | H10: Enterprise | J10: Revenue ($M) | M10: EBITDA ($M) | P10: Net Income ($M) | R10: Revenue | S10: EBITDA | U10: EBITDA Margin
B11: Company Name: | C11: Ticker: | D11: Price ($) | E11: Value ($M) | F11: Beta | G11: Tax Rate | H11: Value ($M) | I11: TTM | J11: ='3_Statment_model'!$H$6 -> 46295 | K11: ='3_Statment_model'!$I$6 -> 46660 | L11: TTM | M11: ='3_Statment_model'!$H$6 -> 46295 | N11: ='3_Statment_model'!$I$6 -> 46660 | O11: TTM | P11: ='3_Statment_model'!$H$6 -> 46295 | Q11: ='3_Statment_model'!$I$6 -> 46660 | R11: Growth | S11: Growth | T11: TTM | U11: ='3_Statment_model'!$H$6 -> 46295 | V11: ='3_Statment_model'!$I$6 -> 46660
B12: Sodexo | C12: SW | D12: 65.87 | E12: 9580 | F12: 0.19 | G12: 0.259 | H12: 13200 | I12: 27244 | J12: 27494 | K12: 28449 | L12: 1506 | M12: 1472 | N12: 1545 | O12: 518 | P12: 287 | Q12: 365 | R12: =(K12-J12)/J12 -> 0.034734851 | S12: =(N12-M12)/M12 -> 0.049592391 | T12: =L12/I12 -> 0.055278226 | U12: =M12/J12 -> 0.053538954 | V12: =N12/K12 -> 0.054307709
B13: Aramark | C13: ARMK | D13: 56.97 | E13: 14980 | F13: 1.18 | G13: 0.257 | H13: 19620 | I13: 19414 | J13: 19970 | K13: 21412 | L13: 1345 | M13: 1540 | N13: 1724 | O13: 357 | P13: 487.2 | Q13: 637.3 | R13: =(K13-J13)/J13 -> 0.072208312 | S13: =(N13-M13)/M13 -> 0.11948052 | T13: =L13/I13 -> 0.069279901 | U13: =M13/J13 -> 0.077115674 | V13: =N13/K13 -> 0.080515599
B14: Elior Group | C14: ELIOR | D14: 2.44 | E14: 616 | F14: 1.87 | G14: 0.322 | H14: 1920 | I14: 7056 | J14: 7135 | K14: 7351 | L14: 374 | M14: 389 | N14: 443 | O14: 76 | P14: 22 | Q14: 67 | R14: =(K14-J14)/J14 -> 0.030273301 | S14: =(N14-M14)/M14 -> 0.13881748 | T14: =L14/I14 -> 0.053004535 | U14: =M14/J14 -> 0.054519972 | V14: =N14/K14 -> 0.06026391
B15: ISS Group | C15: ISS | D15: 44.32 | E15: 6950 | F15: 0.85 | G15: 0.206 | H15: 9160 | I15: 13060 | J15: 13922 | K15: 14659 | L15: 882 | M15: 975 | N15: 1036 | O15: 401 | P15: 465 | Q15: 500 | R15: =(K15-J15)/J15 -> 0.052937796 | S15: =(N15-M15)/M15 -> 0.062564103 | T15: =L15/I15 -> 0.067534456 | U15: =M15/J15 -> 0.070033041 | V15: =N15/K15 -> 0.070673307
B16: SSP Group | C16: SSPG | D16: 268.71 | E16: 2040 | F16: 0.91 | G16: 0.225 | H16: 4670 | I16: 3741 | J16: 5044 | K16: 5396 | L16: 810 | M16: 1005 | N16: 1070 | O16: -39 | P16: 126 | Q16: 151 | R16: =(K16-J16)/J16 -> 0.069785884 | S16: =(N16-M16)/M16 -> 0.064676617 | T16: =L16/I16 -> 0.21651965 | U16: =M16/J16 -> 0.19924663 | V16: =N16/K16 -> 0.19829503
B18: Maximum | D18: =MAX(D12:D16) -> 268.71 | E18: =MAX(E12:E16) -> 14980 | H18: =MAX(H12:H16) -> 19620 | I18: =MAX(I12:I16) -> 27244 | J18: =MAX(J12:J16) -> 27494 | K18: =MAX(K12:K16) -> 28449 | L18: =MAX(L12:L16) -> 1506 | M18: =MAX(M12:M16) -> 1540 | N18: =MAX(N12:N16) -> 1724 | O18: =MAX(O12:O16) -> 518 | ... V18: =MAX(V12:V16) -> 0.19829503
B19: 75th Percentile | D19: =QUARTILE(D12:D16,3) -> 65.87 | E19: =QUARTILE(E12:E16,3) -> 9580 | H19: =QUARTILE(H12:H16,3) -> 13200 | I19: =QUARTILE(I12:I16,3) -> 19414 | J19: =QUARTILE(J12:J16,3) -> 19970 | K19: =QUARTILE(K12:K16,3) -> 21412 | L19: =QUARTILE(L12:L16,3) -> 1345 | M19: =QUARTILE(M12:M16,3) -> 1472 | N19: =QUARTILE(N12:N16,3) -> 1545 | O19: =QUARTILE(O12:O16,3) -> 401 | ... V19: =QUARTILE(V12:V16,3) -> 0.080515599
B20: Median | D20: =MEDIAN(D12:D16) -> 56.97 | E20: =MEDIAN(E12:E16) -> 6950 | H20: =MEDIAN(H12:H16) -> 9160 | I20: =MEDIAN(I12:I16) -> 13060 | J20: =MEDIAN(J12:J16) -> 13922 | K20: =MEDIAN(K12:K16) -> 14659 | L20: =MEDIAN(L12:L16) -> 882 | M20: =MEDIAN(M12:M16) -> 1005 | N20: =MEDIAN(N12:N16) -> 1070 | O20: =MEDIAN(O12:O16) -> 357 | ... V20: =MEDIAN(V12:V16) -> 0.070673307
B21: 25th Percentile | D21: =QUARTILE(D12:D16,1) -> 44.32 | E21: =QUARTILE(E12:E16,1) -> 2040 | H21: =QUARTILE(H12:H16,1) -> 4670 | I21: =QUARTILE(I12:I16,1) -> 7056 | J21: =QUARTILE(J12:J16,1) -> 7135 | K21: =QUARTILE(K12:K16,1) -> 7351 | L21: =QUARTILE(L12:L16,1) -> 810 | M21: =QUARTILE(M12:M16,1) -> 975 | N21: =QUARTILE(N12:N16,1) -> 1036 | O21: =QUARTILE(O12:O16,1) -> 76 | ... V21: =QUARTILE(V12:V16,1) -> 0.06026391
B22: Minimum | D22: =MIN(D12:D16) -> 2.44 | E22: =MIN(E12:E16) -> 616 | H22: =MIN(H12:H16) -> 1920 | I22: =MIN(I12:I16) -> 3741 | J22: =MIN(J12:J16) -> 5044 | K22: =MIN(K12:K16) -> 5396 | L22: =MIN(L12:L16) -> 374 | M22: =MIN(M12:M16) -> 389 | N22: =MIN(N12:N16) -> 443 | O22: =MIN(O12:O16) -> -39 | ... V22: =MIN(V12:V16) -> 0.054307709
B24: Compass Group | C24: CPG | D24: =Valuation_Summary!E6 -> 31.71 | E24: =DCF!E8*DCF!E9 -> 56602.35 | F24: 0.65 | G24: ='3_Statment_model'!G21 -> 0.27244582 | H24: =DCF!E20 -> 62924.35 | I24: 48485 | J24: ='3_Statment_model'!H127 -> 49755.6 | K24: ='3_Statment_model'!I127 -> 53561.903 | L24: 4473 | M24: ='3_Statment_model'!H226 -> 4523.7155 | N24: ='3_Statment_model'!I226 -> 4896.7332 | O24: 2018 | P24: ='3_Statment_model'!H142 -> 2125.5044 | Q24: ='3_Statment_model'!I142 -> 2356.5913 | R24: =(K24-J24)/J24 -> 0.0765 | S24: =(N24-M24)/M24 -> 0.082458266 | T24: =L24/I24 -> 0.092255337 | U24: =M24/J24 -> 0.09091872 | V24: =N24/K24 -> 0.091421942
B26: Valuation Statistics: | E26: Enterprise Value / | H26: Enterprise Value /
E27: Revenue | H27: EBITDA | K27: P/E
B28: Company Name: | C28: Ticker: | D28: TTM | E28: ='3_Statment_model'!$H$6 -> 46295 | F28: ='3_Statment_model'!$I$6 -> 46660 | G28: TTM | H28: ='3_Statment_model'!$H$6 -> 46295 | I28: ='3_Statment_model'!$I$6 -> 46660 | J28: TTM | K28: ='3_Statment_model'!$H$6 -> 46295 | L28: ='3_Statment_model'!$I$6 -> 46660
B29: =B12 -> Sodexo | C29: =C12 -> SW | D29: =IF($H12/I12<0,"NM",$H12/I12) -> 0.48451035 | E29: =IF($H12/J12<0,"NM",$H12/J12) -> 0.48010475 | F29: =IF($H12/K12<0,"NM",$H12/K12) -> 0.46398819 | G29: =IF($H12/L12<0,"NM",$H12/L12) -> 8.7649402 | H29: =IF($H12/M12<0,"NM",$H12/M12) -> 8.9673913 | I29: =IF($H12/N12<0,"NM",$H12/N12) -> 8.5436893 | J29: =IF($E12/O12<0,"NM",$E12/O12) -> 18.494208 | K29: =IF($E12/P12<0,"NM",$E12/P12) -> 33.379791 | L29: =IF($E12/Q12<0,"NM",$E12/Q12) -> 26.246575
B30: =B13 -> Aramark | C30: =C13 -> ARMK | D30: =IF($H13/I13<0,"NM",$H13/I13) -> 1.0106109 | E30: =IF($H13/J13<0,"NM",$H13/J13) -> 0.98247371 | F30: =IF($H13/K13<0,"NM",$H13/K13) -> 0.91630861 | G30: =IF($H13/L13<0,"NM",$H13/L13) -> 14.587361 | H30: =IF($H13/M13<0,"NM",$H13/M13) -> 12.74026 | I30: =IF($H13/N13<0,"NM",$H13/N13) -> 11.38051 | J30: =IF($E13/O13<0,"NM",$E13/O13) -> 41.960784 | K30: =IF($E13/P13<0,"NM",$E13/P13) -> 30.747126 | L30: =IF($E13/Q13<0,"NM",$E13/Q13) -> 23.505413
B31: =B14 -> Elior Group | C31: =C14 -> ELIOR | D31: =IF($H14/I14<0,"NM",$H14/I14) -> 0.27210884 | E31: =IF($H14/J14<0,"NM",$H14/J14) -> 0.26909601 | F31: =IF($H14/K14<0,"NM",$H14/K14) -> 0.26118895 | G31: =IF($H14/L14<0,"NM",$H14/L14) -> 5.1336898 | H31: =IF($H14/M14<0,"NM",$H14/M14) -> 4.9357326 | I31: =IF($H14/N14<0,"NM",$H14/N14) -> 4.3340858 | J31: =IF($E14/O14<0,"NM",$E14/O14) -> 8.1052632 | K31: =IF($E14/P14<0,"NM",$E14/P14) -> 28 | L31: =IF($E14/Q14<0,"NM",$E14/Q14) -> 9.1940299
B32: =B15 -> ISS Group | C32: =C15 -> ISS | D32: =IF($H15/I15<0,"NM",$H15/I15) -> 0.70137825 | E32: =IF($H15/J15<0,"NM",$H15/J15) -> 0.65795144 | F32: =IF($H15/K15<0,"NM",$H15/K15) -> 0.62487209 | G32: =IF($H15/L15<0,"NM",$H15/L15) -> 10.385488 | H32: =IF($H15/M15<0,"NM",$H15/M15) -> 9.3948718 | I32: =IF($H15/N15<0,"NM",$H15/N15) -> 8.8416988 | J32: =IF($E15/O15<0,"NM",$E15/O15) -> 17.331671 | K32: =IF($E15/P15<0,"NM",$E15/P15) -> 14.946237 | L32: =IF($E15/Q15<0,"NM",$E15/Q15) -> 13.9
B33: =B16 -> SSP Group | C33: =C16 -> SSPG | D33: =IF($H16/I16<0,"NM",$H16/I16) -> 1.2483293 | E33: =IF($H16/J16<0,"NM",$H16/J16) -> 0.9258525 | F33: =IF($H16/K16<0,"NM",$H16/K16) -> 0.86545589 | G33: =IF($H16/L16<0,"NM",$H16/L16) -> 5.7654321 | H33: =IF($H16/M16<0,"NM",$H16/M16) -> 4.6467662 | I33: =IF($H16/N16<0,"NM",$H16/N16) -> 4.364486 | J33: =IF($E16/O16<0,"NM",$E16/O16) -> NM | K33: =IF($E16/P16<0,"NM",$E16/P16) -> 16.190476 | L33: =IF($E16/Q16<0,"NM",$E16/Q16) -> 13.509934
B35: Maximum | D35: =MAX(D29:D33) -> 1.2483293 | E35: =MAX(E29:E33) -> 0.98247371 | F35: =MAX(F29:F33) -> 0.91630861 | G35: =MAX(G29:G33) -> 14.587361 | H35: =MAX(H29:H33) -> 12.74026 | I35: =MAX(I29:I33) -> 11.38051 | J35: =MAX(J29:J33) -> 41.960784 | K35: =MAX(K29:K33) -> 33.379791 | L35: =MAX(L29:L33) -> 26.246575
B36: 75th Percentile | D36: =QUARTILE(D29:D33,3) -> 1.0106109 | E36: =QUARTILE(E29:E33,3) -> 0.9258525 | F36: =QUARTILE(F29:F33,3) -> 0.86545589 | G36: =QUARTILE(G29:G33,3) -> 10.385488 | H36: =QUARTILE(H29:H33,3) -> 9.3948718 | I36: =QUARTILE(I29:I33,3) -> 8.8416988 | J36: =QUARTILE(J29:J33,3) -> 24.360852 | K36: =QUARTILE(K29:K33,3) -> 30.747126 | L36: =QUARTILE(L29:L33,3) -> 23.505413
B37: Median | D37: =MEDIAN(D29:D33) -> 0.70137825 | E37: =MEDIAN(E29:E33) -> 0.65795144 | F37: =MEDIAN(F29:F33) -> 0.62487209 | G37: =MEDIAN(G29:G33) -> 8.7649402 | H37: =MEDIAN(H29:H33) -> 8.9673913 | I37: =MEDIAN(I29:I33) -> 8.5436893 | J37: =MEDIAN(J29:J33) -> 17.91294 | K37: =MEDIAN(K29:K33) -> 28 | L37: =MEDIAN(L29:L33) -> 13.9
B38: 25th Percentile | D38: =QUARTILE(D29:D33,1) -> 0.48451035 | E38: =QUARTILE(E29:E33,1) -> 0.48010475 | F38: =QUARTILE(F29:F33,1) -> 0.46398819 | G38: =QUARTILE(G29:G33,1) -> 5.7654321 | H38: =QUARTILE(H29:H33,1) -> 4.9357326 | I38: =QUARTILE(I29:I33,1) -> 4.364486 | J38: =QUARTILE(J29:J33,1) -> 15.025069 | K38: =QUARTILE(K29:K33,1) -> 16.190476 | L38: =QUARTILE(L29:L33,1) -> 13.509934
B39: Minimum | D39: =MIN(D29:D33) -> 0.27210884 | E39: =MIN(E29:E33) -> 0.26909601 | F39: =MIN(F29:F33) -> 0.26118895 | G39: =MIN(G29:G33) -> 5.1336898 | H39: =MIN(H29:H33) -> 4.6467662 | I39: =MIN(I29:I33) -> 4.3340858 | J39: =MIN(J29:J33) -> 8.1052632 | K39: =MIN(K29:K33) -> 14.946237 | L39: =MIN(L29:L33) -> 9.1940299
B41: Compass Group | C41: CPG | D41: =IF($H24/I24<0,"NM",$H24/I24) -> 1.2978107 | E41: =IF($H24/J24<0,"NM",$H24/J24) -> 1.2646687 | F41: =IF($H24/K24<0,"NM",$H24/K24) -> 1.1747967 | G41: =IF($H24/L24<0,"NM",$H24/L24) -> 14.067594 | H41: =IF($H24/M24<0,"NM",$H24/M24) -> 13.909882 | I41: =IF($H24/N24<0,"NM",$H24/N24) -> 12.850271 | J41: =IF($E24/O24<0,"NM",$E24/O24) -> 28.048736 | K41: =IF($E24/P24<0,"NM",$E24/P24) -> 26.630079 | L41: =IF($E24/Q24<0,"NM",$E24/Q24) -> 24.018739
D45: 75th | F45: 25th | H45: Applicable | J45: 75th | L45: 25th
C46: Maximum | D46: Percentile | E46: Median | F46: Percentile | G46: Minimum | H46: Company | I46: Maximum | J46: Percentile | K46: Median | L46: Percentile | M46: Minimum
B47: Methodology Name | C47: Multiple | D47: Multiple | E47: Multiple | F47: Multiple | G47: Multiple | H47: Figure | I47: Multiple | J47: Multiple | K47: Multiple | L47: Multiple | M47: Multiple
B48: TTM TEV / Revenue: | C48: {=TRANSPOSE(D35:L39)} -> 1.2483293 | D48: 1.0106109 | E48: 0.70137825 | F48: 0.48451035 | G48: 0.27210884 | H48: {=TRANSPOSE(I24:Q24)} -> 48485 | I48: =((C48*$H48)-SUM($D$59:$D$64))/$D$67 -> 30.365965 | J48: =((D48*$H48)-SUM($D$59:$D$64))/$D$67 -> 23.908946 | K48: =((E48*$H48)-SUM($D$59:$D$64))/$D$67 -> 15.509426 | L48: =((F48*$H48)-SUM($D$59:$D$64))/$D$67 -> 9.6187587 | M48: =((G48*$H48)-SUM($D$59:$D$64))/$D$67 -> 3.8494102
B49: ="FY26 TEV / Revenue:" -> FY26 TEV / Revenue: | C49: 0.98247371 | D49: 0.9258525 | E49: 0.65795144 | F49: 0.48010475 | G49: 0.26909601 | H49: 49755.6 | I49: =((C49*$H49)-SUM($D$59:$D$64))/$D$67 -> 23.844016 | J49: =((D49*$H49)-SUM($D$59:$D$64))/$D$67 -> 22.26574 | K49: =((E49*$H49)-SUM($D$59:$D$64))/$D$67 -> 14.79819 | L49: =((F49*$H49)-SUM($D$59:$D$64))/$D$67 -> 9.8408403 | M49: =((G49*$H49)-SUM($D$59:$D$64))/$D$67 -> 3.9591223
B50: ="FY27 TEV / Revenue:" -> FY27 TEV / Revenue: | C50: 0.91630861 | D50: 0.86545589 | E50: 0.62487209 | F50: 0.46398819 | G50: 0.26118895 | H50: 53561.903 | I50: =((C50*$H50)-SUM($D$59:$D$64))/$D$67 -> 23.953632 | J50: =((D50*$H50)-SUM($D$59:$D$64))/$D$67 -> 22.427711 | K50: =((E50*$H50)-SUM($D$59:$D$64))/$D$67 -> 15.208593 | L50: =((F50*$H50)-SUM($D$59:$D$64))/$D$67 -> 10.381003 | M50: =((G50*$H50)-SUM($D$59:$D$64))/$D$67 -> 4.2956737
B51: TTM TEV / EBITDA: | C51: 14.587361 | D51: 10.385488 | E51: 8.7649402 | F51: 5.7654321 | G51: 5.1336898 | H51: 4473 | I51: =((C51*$H51)-SUM($D$59:$D$64))/$D$67 -> 33.012473 | J51: =((D51*$H51)-SUM($D$59:$D$64))/$D$67 -> 22.483073 | K51: =((E51*$H51)-SUM($D$59:$D$64))/$D$67 -> 18.422172 | L51: =((F51*$H51)-SUM($D$59:$D$64))/$D$67 -> 10.905758 | M51: =((G51*$H51)-SUM($D$59:$D$64))/$D$67 -> 9.3226861
B52: ="FY26 TEV / EBITDA:" -> FY26 TEV / EBITDA: | C52: 12.74026 | D52: 9.3948718 | E52: 8.9673913 | F52: 4.9357326 | G52: 4.6467662 | H52: 4523.7155 | I52: =((C52*$H52)-SUM($D$59:$D$64))/$D$67 -> 28.745832 | J52: =((D52*$H52)-SUM($D$59:$D$64))/$D$67 -> 20.267634 | K52: =((E52*$H52)-SUM($D$59:$D$64))/$D$67 -> 19.184273 | L52: =((F52*$H52)-SUM($D$59:$D$64))/$D$67 -> 8.9668628 | M52: =((G52*$H52)-SUM($D$59:$D$64))/$D$67 -> 8.2345367
B53: ="FY27 TEV / EBITDA:" -> FY27 TEV / EBITDA: | C53: 11.38051 | D53: 8.8416988 | E53: 8.5436893 | F53: 4.364486 | G53: 4.3340858 | H53: 4896.7332 | I53: =((C53*$H53)-SUM($D$59:$D$64))/$D$67 -> 27.678052 | J53: =((D53*$H53)-SUM($D$59:$D$64))/$D$67 -> 20.713412 | K53: =((E53*$H53)-SUM($D$59:$D$64))/$D$67 -> 19.895892 | L53: =((F53*$H53)-SUM($D$59:$D$64))/$D$67 -> 8.4312176 | M53: =((G53*$H53)-SUM($D$59:$D$64))/$D$67 -> 8.3478217
B54: TTM P / E: | C54: 41.960784 | D54: 24.360852 | E54: 17.91294 | F54: 15.025069 | G54: 8.1052632 | H54: 2018 | I54: =(C54*$H54)/$D$67 -> 47.438018 | J54: =(D54*$H54)/$D$67 -> 27.540728 | K54: =(E54*$H54)/$D$67 -> 20.251155 | L54: =(F54*$H54)/$D$67 -> 16.986324 | M54: =(G54*$H54)/$D$67 -> 9.1632611
B55: ="FY 26 P / E:" -> FY 26 P / E: | C55: 33.379791 | D55: 30.747126 | E55: 28 | F55: 16.190476 | G55: 14.946237 | H55: 2125.5044 | I55: =(C55*$H55)/$D$67 -> 39.747279 | J55: =(D55*$H55)/$D$67 -> 36.61241 | K55: =(E55*$H55)/$D$67 -> 33.341245 | L55: =(F55*$H55)/$D$67 -> 19.278951 | M55: =(G55*$H55)/$D$67 -> 17.797362
B56: ="FY 27 P / E:" -> FY 27 P / E: | C56: 26.246575 | D56: 23.505413 | E56: 13.9 | F56: 13.509934 | G56: 9.1940299 | H56: 2356.5913 | I56: =(C56*$H56)/$D$67 -> 34.651232 | J56: =(D56*$H56)/$D$67 -> 31.032298 | K56: =(E56*$H56)/$D$67 -> 18.351047 | L56: =(F56*$H56)/$D$67 -> 17.836074 | M56: =(G56*$H56)/$D$67 -> 12.138135
B58: Current Equity Value: | C58: $ M | D58: =DCF!E8*DCF!E9 -> 56602.35
B59: (-) Cash & Investments: | C59: $ M | D59: =DCF!E14 -> -575
B60: (+) Debt: | C60: $ M | D60: =DCF!E15 -> 5426
B61: (+) Preferred Stock: | C61: $ M | D61: =DCF!E16 -> 0
B62: (+) Leases: | C62: $ M | D62: =DCF!E17 -> 1566
B63: (+) Noncontrolling Interests: | C63: $ M | D63: =DCF!E18 -> 107
B64: (-) Net Pension Asset: | C64: $ M | D64: =DCF!E19 -> -202
B65: Current Enterprise Value: | C65: $ M | D65: =SUM(D58:D64) -> 62924.35
B67: Diluted Shares Outstanding: | D67: =DCF!E9 -> 1785

Sheet LBO
B2: Transaction Assumptions: | D2: Units:
C3: Company Name: | D3: Name | E3: =Valuation_Summary!E2 -> Compass Group
C4: Last Historical Year: | D4: Date | E4: =Valuation_Summary!E5 -> 45930
C6: Undisturbed Share Price: | D6: $ | E6: =Valuation_Summary!E6 -> 31.71
C7: Premium Paid: | D7: % | E7: 0.25
C8: Offer Price per Share: | D8: $ | E8: =E6*(1+E7) -> 39.6375
C10: Diluted Shares Outstanding: | D10: M Shares | E10: =DCF!E9 -> 1785
C12: Purchase Equity Value: | D12: $ M | E12: =E8*E10 -> 70752.938
C13: (-) Cash & Investments: | D13: $ M | E13: =DCF!E14 -> -575
C14: (+) Debt: | D14: $ M | E14: =DCF!E15 -> 5426
C15: (+) Preferred Stock: | D15: $ M | E15: =DCF!E16 -> 0
C16: (+) Leases: | D16: $ M | E16: =DCF!E17 -> 1566
C17: (+) Noncontrolling Interests: | D17: $ M | E17: =DCF!E18 -> 107
C18: (-) Net Pension Asset: | D18: $ M | E18: =DCF!E19 -> -202
C19: Purchase Enterprise Value: | D19: $ M | E19: =SUM(E12:E18) -> 77074.938
G20: Selected Operating Scenario: | M20: Name | N20: Base
C21: EBITDA: | D21: $ M | E21: =G67-G64 -> 4154 | G21: Management Rollover: | M21: % | N21: 0.1
C22: Purchase TEV / EBITDA Multiple: | D22: x | E22: =E19/E21 -> 18.55439 | G22: Minimum Cash Balance: | M22: $ M | N22: 300
G23: Tax Rate: | M23: % | N23: ='3_Statment_model'!H21 -> 0.27679138
C24: Normalised EBITDA: | D24: $ M | E24: =E21-G65-G66 -> 4485
C25: Normalised Purchase TEV / EBITDA Multiple: | D25: x | E25: =E19/E24 -> 17.185047 | G25: Exit Year: | M25: Date | N25: 47756
C27: Advisory Fee % Purchase Equity Value: | D27: % | E27: 0.01 | G27: Year 3 EBITDA Exit Multiple:
C28: Debt Issuance Fee %: | D28: % | E28: 0.02 | G28: Upside | M28: x | N28: 17.5
C29: Amortization Period: | D29: Years | E29: 7 | G29: Base | M29: x | N29: 15
G30: Downside | M30: x | N30: 13
C31: Legal and Other Fees: | D31: $ M | E31: 25 | G31: Selected Scenario: | M31: x | N31: =INDEX(N28:N30,MATCH(N20,$G28:$G30,0),1) -> 15
B33: Sources & Uses Schedule:
C35: Sources of Funds: | D35: $M | E35: x EBITDA | F35: % Sources | H35: Uses of Funds: | K35: $M | L35: x EBITDA
C36: Revolver: | D36: =E36*$E$24 -> 0 | E36: 0 | F36: =D36/$D$43 -> 0 | H36: Purchase Equity Value: | K36: =E12 -> 70752.938 | L36: =K36/$E$24 -> 15.77546
C37: Term Loan A: | D37: =E37*$E$24 -> 8970 | E37: 2 | F37: =D37/$D$43 -> 0.11575012 | H37: Assume/Replace Target's Debt: | K37: =-G100-G107 -> 5426 | L37: =K37/$E$24 -> 1.2098105
C38: Term Loan B: | D38: =E38*$E$24 -> 13455 | E38: 3 | F38: =D38/$D$43 -> 0.17362519 | H38: Transaction Fees: | K38: =E31+E27*E12 -> 732.52937 | L38: =K38/$E$24 -> 0.16332873
C39: Subordinated Notes: | D39: =E39*$E$24 -> 6727.5 | E39: 1.5 | F39: =D39/$D$43 -> 0.086812594 | H39: Financing Fees: | K39: =E28*SUM(D36:D39) -> 583.05 | L39: =K39/$E$24 -> 0.13
C40: Management Rollover: | D40: =N21*E12 -> 7075.2938 | E40: =D40/$E$24 -> 1.577546 | F40: =D40/$D$43 -> 0.091300572 | H40: Total Uses: | K40: =SUM(K36:K39) -> 77494.517 | L40: =SUM(L36:L39) -> 17.278599
C41: Excess Cash: | D41: =MAX(G93-N22,0) -> 275 | E41: =D41/$E$24 -> 0.061315496 | F41: =D41/$D$43 -> 0.0035486382
C42: Investor Equity: | D42: =K40-SUM(D36:D41) -> 40991.723 | E42: =D42/$E$24 -> 9.1397376 | F42: =D42/$D$43 -> 0.52896288
C43: Total Sources: | D43: =SUM(D36:D42) -> 77494.517 | E43: =SUM(E36:E42) -> 17.278599 | F43: =SUM(F36:F42) -> 1
C45: Ownership Details: | D45: $M | E45: %
C46: Management: | D46: =D40 -> 7075.2938 | E46: =D46/$D$48 -> 0.14719644
C47: Sponsor: | D47: =D42 -> 40991.723 | E47: =D47/$D$48 -> 0.85280356
C48: Total Equity: | D48: =SUM(D46:D47) -> 48067.017 | E48: =SUM(E46:E47) -> 1
B50: Goodwill Creation & Purchase Price Allocation:
C52: Goodwill Calculation: | E52: $M
C53: Equity Purchase Price: | E53: =E12 -> 70752.938
C54: (-) Seller's Common Book Value: | E54: =-G117 -> -7653
C55: (+) Write-Off of Existing Goodwill: | E55: =G83 -> 7687
C56: Total Allocable Purchase Premium: | E56: =SUM(E53:E55) -> 70786.938
F59: Historical: | H59: Transaction Adjustments: | M59: Projected:
B60: Income Statement: | D60: Units: | E60: =EOMONTH(F60,-12) -> 45199 | F60: =EOMONTH(G60,-12) -> 45565 | G60: =E4 -> 45930 | H60: Debit | I60: Credit | J60: =G60 -> 45930 | K60: =EOMONTH(G60,12) -> 46295 | L60: =EOMONTH(K60,12) -> 46660 | M60: =EOMONTH(L60,12) -> 47026 | N60: =EOMONTH(M60,12) -> 47391 | O60: =EOMONTH(N60,12) -> 47756
C61: Revenue: | D61: $M | E61: ='3_Statment_model'!E127 -> 37907 | F61: ='3_Statment_model'!F127 -> 42002 | G61: ='3_Statment_model'!G127 -> 46070 | K61: ='3_Statment_model'!H127 -> 49755.6 | L61: ='3_Statment_model'!I127 -> 53561.903 | M61: ='3_Statment_model'!J127 -> 57471.922 | N61: ='3_Statment_model'!K127 -> 61466.221 | O61: ='3_Statment_model'!L127 -> 65522.992
C62: (-) Direct Costs: | D62: $M | E62: ='3_Statment_model'!E128 -> -12254 | F62: ='3_Statment_model'!F128 -> -13293 | G62: ='3_Statment_model'!G128 -> -14212 | K62: ='3_Statment_model'!H128 -> -15225.214 | L62: ='3_Statment_model'!I128 -> -16282.819 | M62: ='3_Statment_model'!J128 -> -17356.521 | N62: ='3_Statment_model'!K128 -> -18439.866 | O62: ='3_Statment_model'!L128 -> -19656.897
C63: (-) SG&A: | D63: $M | E63: ='3_Statment_model'!E129 -> -22175 | F63: ='3_Statment_model'!F129 -> -24711 | G63: ='3_Statment_model'!G129 -> -27373 | K63: ='3_Statment_model'!H129 -> -29654.338 | L63: ='3_Statment_model'!I129 -> -32030.018 | M63: ='3_Statment_model'!J129 -> -34483.153 | N63: ='3_Statment_model'!K129 -> -36879.733 | O63: ='3_Statment_model'!L129 -> -39313.795
C64: (-) Depreciation and Amortisation: | D64: $M | E64: ='3_Statment_model'!E130 -> -952 | F64: ='3_Statment_model'!F130 -> -1050 | G64: ='3_Statment_model'!G130 -> -1190 | K64: ='3_Statment_model'!H130 -> -1355.043 | L64: ='3_Statment_model'!I130 -> -1416.4544 | M64: ='3_Statment_model'!J130 -> -1490.9434 | N64: ='3_Statment_model'!K130 -> -1576.6617 | O64: ='3_Statment_model'!L130 -> -1672.5334
C65: (-) Restructuring / Integration: | D65: $M | E65: ='3_Statment_model'!E131 -> -281 | F65: ='3_Statment_model'!F131 -> -408 | G65: ='3_Statment_model'!G131 -> -368 | K65: ='3_Statment_model'!H131 -> -352.33333 | L65: ='3_Statment_model'!I131 -> -352.33333 | M65: ='3_Statment_model'!J131 -> -352.33333 | N65: ='3_Statment_model'!K131 -> -352.33333 | O65: ='3_Statment_model'!L131 -> -352.33333
C66: (+) Share of Results of Joint Ventures and Associates: | D66: $M | E66: ='3_Statment_model'!E132 -> 68 | F66: ='3_Statment_model'!F132 -> 44 | G66: ='3_Statment_model'!G132 -> 37 | K66: ='3_Statment_model'!H132 -> 0 | L66: ='3_Statment_model'!I132 -> 0 | M66: ='3_Statment_model'!J132 -> 0 | N66: ='3_Statment_model'!K132 -> 0 | O66: ='3_Statment_model'!L132 -> 0
C67: Operating Income (EBIT): | D67: $M | E67: =SUM(E61:E66) -> 2313 | F67: =SUM(F61:F66) -> 2584 | G67: =SUM(G61:G66) -> 2964 | K67: =SUM(K61:K66) -> 3168.6725 | L67: =SUM(L61:L66) -> 3480.2788 | M67: =SUM(M61:M66) -> 3788.9716 | N67: =SUM(N61:N66) -> 4217.6271 | O67: =SUM(O61:O66) -> 4527.4324
C69: (+) Interest Income: | D69: $M | E69: ='3_Statment_model'!E135 -> 59 | F69: ='3_Statment_model'!F135 -> 68 | G69: ='3_Statment_model'!G135 -> 80 | K69: =K152*K176 -> 10.5 | L69: =L152*L176 -> 10.5 | M69: =M152*M176 -> 10.5 | N69: =N152*N176 -> 11.354874 | O69: =O152*O176 -> 15.356138
C70: (-) Interest Expense: | D70: $M | E70: ='3_Statment_model'!E136 -> -259 | F70: ='3_Statment_model'!F136 -> -393 | G70: ='3_Statment_model'!G136 -> -429 | K70: =-K185-'3_Statment_model'!H105 -> -2282.968 | L70: =-L185-'3_Statment_model'!I105 -> -2261.8115 | M70: =-M185-'3_Statment_model'!J105 -> -2230.3871 | N70: =-N185-'3_Statment_model'!K105 -> -2190.8946 | O70: =-O185-'3_Statment_model'!L105 -> -2138.0976
C71: (-) Amortisation of Financing Fees: | D71: $M | K71: =-MIN($K$39+SUM($J71:J71),$K$39/$E$29) -> -83.292857 | L71: =-MIN($K$39+SUM($J71:K71),$K$39/$E$29) -> -83.292857 | M71: =-MIN($K$39+SUM($J71:L71),$K$39/$E$29) -> -83.292857 | N71: =-MIN($K$39+SUM($J71:M71),$K$39/$E$29) -> -83.292857 | O71: =-MIN($K$39+SUM($J71:N71),$K$39/$E$29) -> -83.292857
C72: (+/-) Net (Loss)/Gain on Sales and Closure of Businesses: | D72: $M | E72: ='3_Statment_model'!E137 -> 24 | F72: ='3_Statment_model'!F137 -> -203 | G72: ='3_Statment_model'!G137 -> -31 | K72: ='3_Statment_model'!H137 -> 0 | L72: ='3_Statment_model'!I137 -> 0 | M72: ='3_Statment_model'!J137 -> 0 | N72: ='3_Statment_model'!K137 -> 0 | O72: ='3_Statment_model'!L137 -> 0
C73: Pre-Tax Income: | D73: $M | E73: =SUM(E67,E69:E72) -> 2137 | F73: =SUM(F67,F69:F72) -> 2056 | G73: =SUM(G67,G69:G72) -> 2584 | K73: =SUM(K67,K69:K72) -> 812.91159 | L73: =SUM(L67,L69:L72) -> 1145.6744 | M73: =SUM(M67,M69:M72) -> 1485.7917 | N73: =SUM(N67,N69:N72) -> 1954.7946 | O73: =SUM(O67,O69:O72) -> 2321.3981
C75: (-) Income Tax Expense: | D75: $M | E75: ='3_Statment_model'!E140 -> -525 | F75: ='3_Statment_model'!F140 -> -642 | G75: ='3_Statment_model'!G140 -> -704 | K75: =-MAX(0,K73*$N$23) -> -225.00692 | L75: =-MAX(0,L73*$N$23) -> -317.1128 | M75: =-MAX(0,M73*$N$23) -> -411.25434 | N75: =-MAX(0,N73*$N$23) -> -541.07028 | O75: =-MAX(0,O73*$N$23) -> -642.54299
C77: Net Income: | D77: $M | E77: =E73+E75 -> 1612 | F77: =F73+F75 -> 1414 | G77: =G73+G75 -> 1880 | K77: =K73+K75 -> 587.90467 | L77: =L73+L75 -> 828.56163 | M77: =M73+M75 -> 1074.5374 | N77: =N73+N75 -> 1413.7243 | O77: =O73+O75 -> 1678.8552
F79: Historical: | H79: Transaction Adjustments: | M79: Projected:
B80: Balance Sheet: | D80: Units: | E80: =EOMONTH(F80,-12) -> 45199 | F80: =EOMONTH(G80,-12) -> 45565 | G80: =E4 -> 45930 | H80: Debit | I80: Credit | J80: =G80 -> 45930 | K80: =EOMONTH(G80,12) -> 46295 | L80: =EOMONTH(K80,12) -> 46660 | M80: =EOMONTH(L80,12) -> 47026 | N80: =EOMONTH(M80,12) -> 47391 | O80: =EOMONTH(N80,12) -> 47756
B81: NET ASSETS:
C82: Non-Current Assets:
C83: Goodwill: | D83: $M | E83: ='3_Statment_model'!E148 -> 6105 | F83: ='3_Statment_model'!F148 -> 6899 | G83: ='3_Statment_model'!G148 -> 7687 | H83: =E56 -> 70786.938 | I83: =-G83 -> -7687 | J83: =SUM(G83:I83) -> 70786.938 | K83: =$J$83 -> 70786.938 | L83: =$J$83 -> 70786.938 | M83: =$J$83 -> 70786.938 | N83: =$J$83 -> 70786.938 | O83: =$J$83 -> 70786.938
C84: Other Intangibles: | D84: $M | E84: ='3_Statment_model'!E149 -> 3796 | F84: ='3_Statment_model'!F149 -> 4850 | G84: ='3_Statment_model'!G149 -> 5664 | H84: 0 | I84: 0 | J84: =SUM(G84:I84) -> 5664 | K84: ='3_Statment_model'!H149 -> 5913.0378 | L84: ='3_Statment_model'!I149 -> 6215.2241 | M84: ='3_Statment_model'!J149 -> 6566.1609 | N84: ='3_Statment_model'!K149 -> 6963.2913 | O84: ='3_Statment_model'!L149 -> 7403.9902
C85: PP&E: | D85: $M | E85: ='3_Statment_model'!E150 -> 1166 | F85: ='3_Statment_model'!F150 -> 1411 | G85: ='3_Statment_model'!G150 -> 1569 | H85: 0 | I85: 0 | J85: =SUM(G85:I85) -> 1569 | K85: ='3_Statment_model'!H150 -> 1670.0789 | L85: ='3_Statment_model'!I150 -> 1795.687 | M85: ='3_Statment_model'!J150 -> 1940.9576 | N85: ='3_Statment_model'!K150 -> 2103.067 | O85: ='3_Statment_model'!L150 -> 2279.759
C86: ROU Assets: | D86: $M | E86: ='3_Statment_model'!E151 -> 992 | F86: ='3_Statment_model'!F151 -> 1144 | G86: ='3_Statment_model'!G151 -> 1377 | H86: 0 | I86: 0 | J86: =SUM(G86:I86) -> 1377 | K86: ='3_Statment_model'!H151 -> 1416.2422 | L86: ='3_Statment_model'!I151 -> 1456.7934 | M86: ='3_Statment_model'!J151 -> 1498.5874 | N86: ='3_Statment_model'!K151 -> 1541.5732 | O86: ='3_Statment_model'!L151 -> 1585.7117
C87: Other Non-Current Assets: | D87: $M | E87: ='3_Statment_model'!E152 -> 2473 | F87: ='3_Statment_model'!F152 -> 2552 | G87: ='3_Statment_model'!G152 -> 2625 | H87: =K39 -> 583.05 | I87: 0 | J87: =SUM(G87:I87) -> 3208.05 | K87: ='3_Statment_model'!H152+$H$87-SUM($K$130:K130) -> 3195.6321 | L87: ='3_Statment_model'!I152+$H$87-SUM($K$130:L130) -> 3182.432 | M87: ='3_Statment_model'!J152+$H$87-SUM($K$130:M130) -> 3168.2884 | N87: ='3_Statment_model'!K152+$H$87-SUM($K$130:N130) -> 3155.8734 | O87: ='3_Statment_model'!L152+$H$87-SUM($K$130:O130) -> 3145.2305
C88: Total Non-Current Assets: | D88: $M | E88: =SUM(E83:E87) -> 14532 | F88: =SUM(F83:F87) -> 16856 | G88: =SUM(G83:G87) -> 18922 | J88: =SUM(J83:J87) -> 82604.988 | K88: =SUM(K83:K87) -> 82981.929 | L88: =SUM(L83:L87) -> 83437.074 | M88: =SUM(M83:M87) -> 83960.932 | N88: =SUM(N83:N87) -> 84550.742 | O88: =SUM(O83:O87) -> 85201.629
C90: Current Assets:
C91: Inventory: | D91: $M | E91: ='3_Statment_model'!E156 -> 692 | F91: ='3_Statment_model'!F156 -> 734 | G91: ='3_Statment_model'!G156 -> 820 | H91: 0 | I91: 0 | J91: =SUM(G91:I91) -> 820 | K91: ='3_Statment_model'!H156 -> 860.41431 | L91: ='3_Statment_model'!I156 -> 920.18218 | M91: ='3_Statment_model'!J156 -> 978.17977 | N91: ='3_Statment_model'!K156 -> 1042.0823 | O91: ='3_Statment_model'!L156 -> 1110.8597
C92: Trade and Other Receivables: | D92: $M | E92: ='3_Statment_model'!E157 -> 5094 | F92: ='3_Statment_model'!F157 -> 5686 | G92: ='3_Statment_model'!G157 -> 6350 | H92: 0 | I92: 0 | J92: =SUM(G92:I92) -> 6350 | K92: ='3_Statment_model'!H157 -> 6766.1088 | L92: ='3_Statment_model'!I157 -> 7283.7161 | M92: ='3_Statment_model'!J157 -> 7794.0738 | N92: ='3_Statment_model'!K157 -> 8358.5996 | O92: ='3_Statment_model'!L157 -> 8910.2672
C93: Cash and Cash Equivalents: | D93: $M | E93: ='3_Statment_model'!E158 -> 1029 | F93: ='3_Statment_model'!F158 -> 623 | G93: ='3_Statment_model'!G158 -> 575 | H93: 0 | I93: =-D41 -> -275 | J93: =SUM(G93:I93) -> 300 | K93: =K159 -> 300 | L93: =L159 -> 300 | M93: =M159 -> 324.42498 | N93: =N159 -> 438.74681 | O93: =O159 -> 541.97826
C94: Other Current Assets: | D94: $M | E94: ='3_Statment_model'!E159 -> 136 | F94: ='3_Statment_model'!F159 -> 450 | G94: ='3_Statment_model'!G159 -> 48 | H94: 0 | I94: 0 | J94: =SUM(G94:I94) -> 48 | K94: ='3_Statment_model'!H159 -> 254.47329 | L94: ='3_Statment_model'!I159 -> 273.9405 | M94: ='3_Statment_model'!J159 -> 293.93816 | N94: ='3_Statment_model'!K159 -> 314.36686 | O94: ='3_Statment_model'!L159 -> 335.11507
C95: Total Current Assets: | D95: $M | E95: =SUM(E91:E94) -> 6951 | F95: =SUM(F91:F94) -> 7493 | G95: =SUM(G91:G94) -> 7793 | J95: =SUM(J91:J94) -> 7518 | K95: =SUM(K91:K94) -> 8180.9964 | L95: =SUM(L91:L94) -> 8777.8388 | M95: =SUM(M91:M94) -> 9390.6167 | N95: =SUM(N91:N94) -> 10153.796 | O95: =SUM(O91:O94) -> 10898.22
C97: Total Assets: | D97: $M | E97: =SUM(E88,E95) -> 21483 | F97: =SUM(F88,F95) -> 24349 | G97: =SUM(G88,G95) -> 26715 | J97: =J88+J95 -> 90122.988 | K97: =SUM(K88,K95) -> 91162.925 | L97: =SUM(L88,L95) -> 92214.913 | M97: =SUM(M88,M95) -> 93351.548 | N97: =SUM(N88,N95) -> 94704.538 | O97: =SUM(O88,O95) -> 96099.849
C99: Current Liabilities:
C100: Short-Term Borrowings: | D100: $M | E100: ='3_Statment_model'!E165 -> -1327 | F100: ='3_Statment_model'!F165 -> -822 | G100: ='3_Statment_model'!G165 -> -1043 | H100: 1043 | I100: 0 | J100: =SUM(G100:I100) -> 0 | K100: =-K206 -> -184.53189 | L100: =-L206 -> -140.44819 | M100: =-M206 -> 0 | N100: =-N206 -> 0 | O100: =-O206 -> 0
C101: Lease Liabilities | D101: $M | E101: ='3_Statment_model'!E166 -> -237 | F101: ='3_Statment_model'!F166 -> -273 | G101: ='3_Statment_model'!G166 -> -338 | H101: 0 | I101: 0 | J101: =SUM(G101:I101) -> -338 | K101: ='3_Statment_model'!H166 -> -334.2504 | L101: ='3_Statment_model'!I166 -> -340.39988 | M101: ='3_Statment_model'!J166 -> -346.76665 | N101: ='3_Statment_model'!K166 -> -353.33846 | O101: ='3_Statment_model'!L166 -> -360.10572
C102: Trade and Other Payables: | D102: $M | E102: ='3_Statment_model'!E167 -> -7166 | F102: ='3_Statment_model'!F167 -> -8172 | G102: ='3_Statment_model'!G167 -> -8639 | H102: 0 | I102: 0 | J102: =SUM(G102:I102) -> -8639 | K102: ='3_Statment_model'!H167 -> -9181.307 | L102: ='3_Statment_model'!I167 -> -9819.0778 | M102: ='3_Statment_model'!J167 -> -10437.958 | N102: ='3_Statment_model'!K167 -> -11119.849 | O102: ='3_Statment_model'!L167 -> -11853.759
C103: Other Current Liabilities: | D103: $M | E103: ='3_Statment_model'!E168 -> -590 | F103: ='3_Statment_model'!F168 -> -805 | G103: ='3_Statment_model'!G168 -> -645 | H103: 0 | I103: 0 | J103: =SUM(G103:I103) -> -645 | K103: ='3_Statment_model'!H168 -> -805.85871 | L103: ='3_Statment_model'!I168 -> -866.30984 | M103: ='3_Statment_model'!J168 -> -928.60543 | N103: ='3_Statment_model'!K168 -> -990.28377 | O103: ='3_Statment_model'!L168 -> -1055.0986
C104: Total Current Liabilities | D104: $M | E104: =SUM(E100:E103) -> -9320 | F104: =SUM(F100:F103) -> -10072 | G104: =SUM(G100:G103) -> -10665 | J104: =SUM(J100:J103) -> -9622 | K104: =SUM(K100:K103) -> -10505.948 | L104: =SUM(L100:L103) -> -11166.236 | M104: =SUM(M100:M103) -> -11713.33 | N104: =SUM(N100:N103) -> -12463.471 | O104: =SUM(O100:O103) -> -13268.963
C106: Non-Current Liabilities
C107: Long-Term Borrowings: | D107: $M | E107: ='3_Statment_model'!E172 -> -2787 | F107: ='3_Statment_model'!F172 -> -3774 | G107: ='3_Statment_model'!G172 -> -4383 | H107: 4383 | I107: =-SUM($D$36:$D$39) -> -29152.5 | J107: =SUM(G107:I107) -> -29152.5 | K107: =-K212-K218-K224 -> -28457.325 | L107: =-L212-L218-L224 -> -27778.969 | M107: =-M212-M218-M224 -> -27044.997 | N107: =-N212-N218-N224 -> -25986.603 | O107: =-O212-O218-O224 -> -24637.984
C108: Lease Liabilities: | D108: $M | E108: ='3_Statment_model'!E173 -> -916 | F108: ='3_Statment_model'!F173 -> -1042 | G108: ='3_Statment_model'!G173 -> -1228 | H108: 0 | I108: 0 | J108: =SUM(G108:I108) -> -1228 | K108: ='3_Statment_model'!H173 -> -1259.9694 | L108: ='3_Statment_model'!I173 -> -1283.15 | M108: ='3_Statment_model'!J173 -> -1307.1498 | N108: ='3_Statment_model'!K173 -> -1331.9225 | O108: ='3_Statment_model'!L173 -> -1357.432
C109: Other Long-Term Liabilities: | D109: $M | E109: ='3_Statment_model'!E174 -> -2160 | F109: ='3_Statment_model'!F174 -> -2555 | G109: ='3_Statment_model'!G174 -> -2679 | H109: 0 | I109: 0 | J109: =SUM(G109:I109) -> -2679 | K109: ='3_Statment_model'!H174 -> -2910.2904 | L109: ='3_Statment_model'!I174 -> -3128.6045 | M109: ='3_Statment_model'!J174 -> -3353.5797 | N109: ='3_Statment_model'!K174 -> -3576.3259 | O109: ='3_Statment_model'!L174 -> -3810.3992
C110: Total Non-Current Liabilities | D110: $M | E110: =SUM(E107:E109) -> -5863 | F110: =SUM(F107:F109) -> -7371 | G110: =SUM(G107:G109) -> -8290 | J110: =SUM(J107:J109) -> -33059.5 | K110: =SUM(K107:K109) -> -32627.585 | L110: =SUM(L107:L109) -> -32190.723 | M110: =SUM(M107:M109) -> -31705.727 | N110: =SUM(N107:N109) -> -30894.851 | O110: =SUM(O107:O109) -> -29805.815
C112: Total Liabilities: | D112: $M | E112: =SUM(E110,E104) -> -15183 | F112: =SUM(F110,F104) -> -17443 | G112: =SUM(G110,G104) -> -18955 | J112: =J104+J110 -> -42681.5 | K112: =K104+K110 -> -43133.533 | L112: =L104+L110 -> -43356.959 | M112: =M104+M110 -> -43419.057 | N112: =N104+N110 -> -43358.322 | O112: =O104+O110 -> -43074.778
C114: Net Assets: | D114: $M | E114: =E97+E112 -> 6300 | F114: =F97+F112 -> 6906 | G114: =G97+G112 -> 7760 | J114: =J97+J112 -> 47441.488 | K114: =K97+K112 -> 48029.392 | L114: =L97+L112 -> 48857.954 | M114: =M97+M112 -> 49932.491 | N114: =N97+N112 -> 51346.215 | O114: =O97+O112 -> 53025.071
B116: EQUITY:
C117: Common Shareholder Equity: | D117: $M | E117: ='3_Statment_model'!E182 -> 6263 | F117: ='3_Statment_model'!F182 -> 6829 | G117: ='3_Statment_model'!G182 -> 7653 | H117: =E54-K38 -> -8385.5294 | I117: =D40+D42 -> 48067.017 | J117: =SUM(G117:I117) -> 47334.488 | K117: =J117+K125+K143+K144 -> 47922.392 | L117: =K117+L125+L143+L144 -> 48750.954 | M117: =L117+M125+M143+M144 -> 49825.491 | N117: =M117+N125+N143+N144 -> 51239.215 | O117: =N117+O125+O143+O144 -> 52918.071
C118: Non-Controlling Interest: | D118: $M | E118: ='3_Statment_model'!E183 -> 37 | F118: ='3_Statment_model'!F183 -> 77 | G118: ='3_Statment_model'!G183 -> 107 | H118: 0 | I118: 0 | J118: =SUM(G118:I118) -> 107 | K118: ='3_Statment_model'!H183 -> 107 | L118: ='3_Statment_model'!I183 -> 107 | M118: ='3_Statment_model'!J183 -> 107 | N118: ='3_Statment_model'!K183 -> 107 | O118: ='3_Statment_model'!L183 -> 107
C120: Total Equity: | D120: $M | E120: =SUM(E117:E118) -> 6300 | F120: =SUM(F117:F118) -> 6906 | G120: =SUM(G117:G118) -> 7760 | J120: =SUM(J117:J118) -> 47441.488 | K120: =SUM(K117:K118) -> 48029.392 | L120: =SUM(L117:L118) -> 48857.954 | M120: =SUM(M117:M118) -> 49932.491 | N120: =SUM(N117:N118) -> 51346.215 | O120: =SUM(O117:O118) -> 53025.071
F122: Historical: | H122: Transaction Adjustments: | M122: Projected:
B123: Cash Flow Statement: | D123: Units: | E123: =EOMONTH(F123,-12) -> 45199 | F123: =EOMONTH(G123,-12) -> 45565 | G123: =E4 -> 45930 | H123: Debit | I123: Credit | J123: =G123 -> 45930 | K123: =EOMONTH(G123,12) -> 46295 | L123: =EOMONTH(K123,12) -> 46660 | M123: =EOMONTH(L123,12) -> 47026 | N123: =EOMONTH(M123,12) -> 47391 | O123: =EOMONTH(N123,12) -> 47756
B124: CASH FLOWS FROM OPERATING ACTIVITIES:
C125: Net Income: | D125: $M | E125: =E77 -> 1612 | F125: =F77 -> 1414 | G125: =G77 -> 1880 | K125: =K77 -> 587.90467 | L125: =L77 -> 828.56163 | M125: =M77 -> 1074.5374 | N125: =N77 -> 1413.7243 | O125: =O77 -> 1678.8552
...

Sheet Imported_Financial_Statements
A1: Income Statement: | F1: Balance Sheet: | K1: Statement of Cash Flows:
A3: Column1 | B3: Column2 | C3: Column3 | D3: Column4 | F3: Column1 | G3: Column2 | H3: Column3 | I3: Column4 | K3: Column1 | L3: Column2 | M3: Column3 | N3: Column4
B4: 2025-09-30 | C4: 2024-09-30 | D4: 2023-09-30 | G4: 2025-09-30 | H4: 2024-09-30 | I4: 2023-09-30 | L4: 2025-09-30 | M4: 2024-09-30 | N4: 2023-09-30
A5: Tax Effect Of Unusual Items | B5: -117151702.786378 | C5: -214520428.015564 | D5: -85362000.0 | F5: Treasury Shares Number | G5: 88102999.0 | H5: 88290717.0 | I5: 70744082.0 | K5: Free Cash Flow | L5: 2474000000.0 | M5: 2234000000.0 | N5: 1828000000.0
A6: Tax Rate For Calcs | B6: 0.272446 | C6: 0.312257 | D6: 0.246 | F6: Ordinary Shares Number | G6: 1697300978.0 | H6: 1697113260.0 | I6: 1714659895.0 | K6: Repurchase Of Capital Stock | L6: -115000000.0 | M6: -577000000.0 | N6: -1148000000.0
A7: Normalized EBITDA | B7: 4582000000.0 | C7: 4098000000.0 | D7: 3657000000.0 | F7: Share Issued | G7: 1785403977.0 | H7: 1785403977.0 | I7: 1785403977.0 | K7: Repayment Of Debt | L7: -882000000.0 | M7: -1592000000.0 | N7: -543000000.0
A8: Total Unusual Items | B8: -430000000.0 | C8: -687000000.0 | D8: -347000000.0 | F8: Net Debt | G8: 4851000000.0 | H8: 3973000000.0 | I8: 3085000000.0 | K8: Issuance Of Debt | L8: 1412000000.0 | M8: 1381000000.0 | N8: 1000000.0
A9: Total Unusual Items Excluding Goodwill | B9: -430000000.0 | C9: -687000000.0 | D9: -347000000.0 | F9: Total Debt | G9: 6992000000.0 | H9: 5911000000.0 | I9: 5267000000.0 | K9: Issuance Of Capital Stock | M9: 0.0 | N9: -19000000.0
A10: Net Income From Continuing Operation Net Minority Interest | B10: 1868000000.0 | C10: 1404000000.0 | D10: 1607000000.0 | F10: Tangible Book Value | G10: -4033000000.0 | H10: -3395000000.0 | I10: -2322000000.0 | K10: Capital Expenditure | L10: -892000000.0 | M10: -901000000.0 | N10: -708000000.0
A11: Reconciled Depreciation | B11: 852000000.0 | C11: 744000000.0 | D11: 670000000.0 | F11: Invested Capital | G11: 13079000000.0 | H11: 11425000000.0 | I11: 10377000000.0 | K11: End Cash Position | L11: 512000000.0 | M11: 593000000.0 | N11: 830000000.0
A12: Reconciled Cost Of Revenue | B12: 30677000000.0 | C12: 28076000000.0 | D12: 25567000000.0 | F12: Working Capital | G12: -2872000000.0 | H12: -2579000000.0 | I12: -2369000000.0 | K12: Other Cash Adjustment Outside Changein Cash | M12: -40000000.0
A13: EBITDA | B13: 4152000000.0 | C13: 3411000000.0 | D13: 3310000000.0 | F13: Net Tangible Assets | G13: -4033000000.0 | H13: -3395000000.0 | I13: -2322000000.0 | K13: Beginning Cash Position | L13: 593000000.0 | M13: 830000000.0 | N13: 1934000000.0
A14: EBIT | B14: 2962000000.0 | C14: 2361000000.0 | D14: 2358000000.0 | F14: Capital Lease Obligations | G14: 1566000000.0 | H14: 1315000000.0 | I14: 1153000000.0 | K14: Effect Of Exchange Rate Changes | L14: 22000000.0 | M14: 59000000.0 | N14: 169000000.0
A15: Net Interest Income | B15: -356000000.0 | C15: -277000000.0 | D15: -175000000.0 | F15: Common Stock Equity | G15: 7653000000.0 | H15: 6829000000.0 | I15: 6263000000.0 | K15: Changes In Cash | L15: -103000000.0 | M15: -296000000.0 | N15: -1273000000.0
A16: Interest Expense | B16: 378000000.0 | C16: 305000000.0 | D16: 221000000.0 | F16: Total Capitalization | G16: 12036000000.0 | H16: 10603000000.0 | I16: 9050000000.0 | K16: Financing Cash Flow | L16: -1045000000.0 | M16: -1942000000.0 | N16: -2580000000.0
A17: Interest Income | B17: 29000000.0 | C17: 30000000.0 | D17: 53000000.0 | F17: Total Equity Gross Minority Interest | G17: 7760000000.0 | H17: 6906000000.0 | I17: 6300000000.0 | K17: Net Other Financing Charges | L17: -140000000.0 | M17: 46000000.0 | N17: 147000000.0
A18: Normalized Income | B18: 2180848297.213622 | C18: 1876479571.984436 | D18: 1868638000.0 | F18: Minority Interest | G18: 107000000.0 | H18: 77000000.0 | I18: 37000000.0 | K18: Cash Dividends Paid | L18: -1047000000.0 | M18: -963000000.0 | N18: -796000000.0
A19: Net Income From Continuing And Discontinued Operation | B19: 1868000000.0 | C19: 1404000000.0 | D19: 1607000000.0 | F19: Stockholders Equity | G19: 7653000000.0 | H19: 6829000000.0 | I19: 6263000000.0 | K19: Common Stock Dividend Paid | L19: -1047000000.0 | M19: -963000000.0 | N19: -796000000.0
A20: Total Expenses | B20: 42775000000.0 | C20: 39054000000.0 | D20: 35339000000.0 | F20: Other Equity Interest | K20: Net Common Stock Issuance | L20: -115000000.0 | M20: -577000000.0 | N20: -1167000000.0
A21: Rent Expense Supplemental | C21: 192000000.0 | D21: 182000000.0 | F21: Fixed Assets Revaluation Reserve | G21: 0.0 | H21: 0.0 | I21: 14000000.0 | K21: Common Stock Payments | L21: -115000000.0 | M21: -577000000.0 | N21: -1148000000.0
A22: Total Operating Income As Reported | B22: 2964000000.0 | C22: 2584000000.0 | D22: 2245000000.0 | F22: Treasury Stock | G22: 2220000000.0 | H22: 2296000000.0 | I22: 1848000000.0 | K22: Common Stock Issuance | M22: 0.0 | N22: -19000000.0
A23: Diluted Average Shares | B23: 1699000000.0 | C23: 1707000000.0 | D23: 1745000000.0 | F23: Retained Earnings | G23: 2302000000.0 | H23: 1574000000.0 | I23: 1018000000.0 | K23: Net Issuance Payments Of Debt | L23: 530000000.0 | M23: -211000000.0 | N23: -542000000.0
A24: Basic Average Shares | B24: 1697000000.0 | C24: 1705000000.0 | D24: 1743000000.0 | F24: Additional Paid In Capital | G24: 828000000.0 | H24: 828000000.0 | I24: 828000000.0 | K24: Net Long Term Debt Issuance | L24: 530000000.0 | M24: -211000000.0 | N24: -542000000.0
A25: Diluted EPS | B25: 1.099 | C25: 0.822 | D25: 0.91873 | F25: Capital Stock | G25: 346000000.0 | H25: 346000000.0 | I25: 346000000.0 | K25: Long Term Debt Payments | L25: -882000000.0 | M25: -1592000000.0 | N25: -543000000.0
A26: Basic EPS | B26: 1.101 | C26: 0.823 | D26: 0.91995 | F26: Common Stock | G26: 346000000.0 | H26: 346000000.0 | I26: 346000000.0 | K26: Long Term Debt Issuance | L26: 1412000000.0 | M26: 1381000000.0 | N26: 1000000.0
A27: Diluted NI Availto Com Stockholders | B27: 1868000000.0 | C27: 1404000000.0 | D27: 1607000000.0 | F27: Total Liabilities Net Minority Interest | G27: 18955000000.0 | H27: 17443000000.0 | I27: 15183000000.0 | K27: Investing Cash Flow | L27: -2424000000.0 | M27: -1489000000.0 | N27: -1229000000.0
A28: Net Income Common Stockholders | B28: 1868000000.0 | C28: 1404000000.0 | D28: 1607000000.0 | F28: Total Non Current Liabilities Net Minority Interest | G28: 8290000000.0 | H28: 7371000000.0 | I28: 5863000000.0 | K28: Net Other Investing Changes | L28: -490000000.0 | M28: -508000000.0 | N28: -380000000.0
A29: Otherunder Preferred Stock Dividend | B29: 0.0 | C29: 0.0 | D29: 0.0 | F29: Other Non Current Liabilities | K29: Interest Received Cfi | L29: 37000000.0 | M29: 39000000.0 | N29: 61000000.0
A30: Net Income | B30: 1868000000.0 | C30: 1404000000.0 | D30: 1607000000.0 | F30: Derivative Product Liabilities | G30: 208000000.0 | H30: 252000000.0 | I30: 253000000.0 | K30: Dividends Received Cfi | L30: 43000000.0 | M30: 65000000.0 | N30: 60000000.0
A31: Minority Interests | B31: -12000000.0 | C31: -10000000.0 | D31: -5000000.0 | F31: Non Current Pension And Other Postretirement Benefit Plans | G31: 1395000000.0 | H31: 1274000000.0 | I31: 983000000.0 | K31: Net Investment Purchase And Sale | L31: -98000000.0 | M31: 328000000.0 | N31: 0.0
A32: Net Income Including Noncontrolling Interests | B32: 1880000000.0 | C32: 1414000000.0 | D32: 1612000000.0 | F32: Non Current Accrued Expenses | G32: 4000000.0 | H32: 9000000.0 | K32: Sale Of Investment | M32: 330000000.0 | N32: 4000000.0
A33: Net Income Continuous Operations | B33: 1880000000.0 | C33: 1414000000.0 | D33: 1612000000.0 | F33: Tradeand Other Payables Non Current | G33: 189000000.0 | H33: 175000000.0 | I33: 443000000.0 | K33: Purchase Of Investment | L33: -98000000.0 | M33: -2000000.0 | N33: -4000000.0
A34: Tax Provision | B34: 704000000.0 | C34: 642000000.0 | D34: 525000000.0 | F34: Non Current Deferred Revenue | G34: 252000000.0 | H34: 214000000.0 | K34: Net Business Purchase And Sale | L34: -1091000000.0 | M34: -568000000.0 | N34: -340000000.0
A35: Pretax Income | B35: 2584000000.0 | C35: 2056000000.0 | D35: 2137000000.0 | F35: Non Current Deferred Taxes Liabilities | G35: 276000000.0 | H35: 287000000.0 | I35: 132000000.0 | K35: Sale Of Business | L35: 166000000.0 | M35: 225000000.0 | N35: 58000000.0
A36: Special Income Charges | B36: -410000000.0 | C36: -620000000.0 | D36: -299000000.0 | F36: Long Term Debt And Capital Lease Obligation | G36: 5611000000.0 | H36: 4816000000.0 | I36: 3703000000.0 | K36: Purchase Of Business | L36: -1257000000.0 | M36: -793000000.0 | N36: -398000000.0
A37: Other Special Charges | B37: 31000000.0 | C37: 203000000.0 | D37: -24000000.0 | F37: Long Term Capital Lease Obligation | G37: 1228000000.0 | H37: 1042000000.0 | I37: 916000000.0 | K37: Net Intangibles Purchase And Sale | L37: -347000000.0 | M37: -329000000.0 | N37: -263000000.0
A38: Write Off | B38: 8000000.0 | C38: 3000000.0 | D38: 77000000.0 | F38: Long Term Debt | G38: 4383000000.0 | H38: 3774000000.0 | I38: 2787000000.0 | K38: Purchase Of Intangibles | L38: -347000000.0 | M38: -329000000.0 | N38: -263000000.0
A39: Impairment Of Capital Assets | C39: 146000000.0 | D39: 60000000.0 | F39: Long Term Provisions | G39: 355000000.0 | H39: 344000000.0 | I39: 349000000.0 | K39: Net PPE Purchase And Sale | L39: -478000000.0 | M39: -491000000.0 | N39: -367000000.0
A40: Restructuring And Mergern Acquisition | B40: 371000000.0 | C40: 414000000.0 | D40: 186000000.0 | F40: Current Liabilities | G40: 10665000000.0 | H40: 10072000000.0 | I40: 9320000000.0 | K40: Sale Of PPE | L40: 67000000.0 | M40: 81000000.0 | N40: 78000000.0
A41: Net Non Operating Interest Income Expense | B41: -356000000.0 | C41: -277000000.0 | D41: -175000000.0 | F41: Other Current Liabilities | K41: Purchase Of PPE | L41: -545000000.0 | M41: -572000000.0 | N41: -445000000.0
A42: Total Other Finance Cost | B42: 7000000.0 | C42: 2000000.0 | D42: 7000000.0 | F42: Current Debt And Capital Lease Obligation | G42: 1381000000.0 | H42: 1095000000.0 | I42: 1564000000.0 | K42: Operating Cash Flow | L42: 3366000000.0 | M42: 3135000000.0 | N42: 2536000000.0
A43: Interest Expense Non Operating | B43: 378000000.0 | C43: 305000000.0 | D43: 221000000.0 | F43: Current Capital Lease Obligation | G43: 338000000.0 | H43: 273000000.0 | I43: 237000000.0 | K43: Taxes Refund Paid | L43: -653000000.0 | M43: -693000000.0 | N43: -539000000.0
A44: Interest Income Non Operating | B44: 29000000.0 | C44: 30000000.0 | D44: 53000000.0 | F44: Current Debt | G44: 1043000000.0 | H44: 822000000.0 | I44: 1327000000.0 | K44: Interest Paid Cfo | L44: -327000000.0 | M44: -267000000.0 | N44: -208000000.0
A45: Operating Income | B45: 3295000000.0 | C45: 2948000000.0 | D45: 2568000000.0 | F45: Current Provisions | G45: 388000000.0 | H45: 370000000.0 | I45: 284000000.0 | K45: Change In Working Capital | L45: -40000000.0 | M45: 186000000.0 | N45: -120000000.0
A46: Operating Expense | B46: 12098000000.0 | C46: 10978000000.0 | D46: 9772000000.0 | F46: Payables | G46: 5322000000.0 | H46: 4952000000.0 | I46: 4616000000.0 | K46: Change In Payable | L46: 468000000.0 | M46: 892000000.0 | N46: 679000000.0
A47: Other Operating Expenses | B47: 7364000000.0 | C47: 6924000000.0 | D47: 6001000000.0 | F47: Other Payable | G47: 579000000.0 | H47: 831000000.0 | I47: 796000000.0 | K47: Change In Inventory | L47: -64000000.0 | M47: -36000000.0 | N47: -119000000.0
A48: Depreciation And Amortization In Income Statement | B48: 1190000000.0 | C48: 1050000000.0 | D48: 952000000.0 | F48: Total Tax Payable | G48: 892000000.0 | H48: 804000000.0 | I48: 880000000.0 | K48: Change In Receivables | L48: -444000000.0 | M48: -670000000.0 | N48: -680000000.0
A49: Amortization | B49: 521000000.0 | C49: 456000000.0 | D49: 416000000.0 | F49: Accounts Payable | G49: 3851000000.0 | H49: 3317000000.0 | I49: 2940000000.0 | K49: Other Non Cash Items | L49: 753000000.0 | M49: 797000000.0 | N49: 624000000.0
A50: Depreciation Income Statement | B50: 669000000.0 | C50: 594000000.0 | D50: 536000000.0 | F50: Total Assets | G50: 26715000000.0 | H50: 24349000000.0 | I50: 21483000000.0 | K50: Stock Based Compensation | L50: 82000000.0 | M50: 68000000.0 | N50: 54000000.0
A51: Selling General And Administration | C51: 11000000.0 | D51: 10000000.0 | F51: Total Non Current Assets | G51: 18922000000.0 | H51: 16856000000.0 | I51: 14532000000.0 | K51: Provisionand Write Offof Assets | L51: -1000000.0 | M51: 7000000.0 | N51: -50000000.0
A52: General And Administrative Expense | C52: 11000000.0 | D52: 10000000.0 | F52: Defined Pension Benefit | G52: 327000000.0 | H52: 542000000.0 | I52: 525000000.0 | K52: Depreciation And Amortization | L52: 852000000.0 | M52: 744000000.0 | N52: 670000000.0
A53: Rent And Landing Fees | C53: 192000000.0 | D53: 182000000.0 | F53: Non Current Prepaid Assets | K53: Amortization Cash Flow | L53: 183000000.0 | M53: 150000000.0 | N53: 134000000.0
A54: Gross Profit | B54: 15393000000.0 | C54: 13926000000.0 | D54: 12340000000.0 | F54: Non Current Deferred Assets | G54: 1665000000.0 | H54: 1525000000.0 | I54: 1316000000.0 | K54: Depreciation | L54: 669000000.0 | M54: 594000000.0 | N54: 536000000.0
A55: Cost Of Revenue | B55: 30677000000.0 | C55: 28076000000.0 | D55: 25567000000.0 | F55: Non Current Deferred Taxes Assets | G55: 246000000.0 | H55: 179000000.0 | I55: 237000000.0 | K55: Pension And Employee Benefit Expense | L55: 22000000.0 | M55: 15000000.0 | N55: -13000000.0
A56: Total Revenue | B56: 46070000000.0 | C56: 42002000000.0 | D56: 37907000000.0 | F56: Financial Assets | G56: 97000000.0 | H56: 69000000.0 | I56: 55000000.0 | K56: Gain Loss On Sale Of PPE | L56: 0.0 | M56: -5000000.0 | N56: -4000000.0
A57: Operating Revenue | B57: 46070000000.0 | C57: 42002000000.0 | D57: 37907000000.0 | F57: Other Investments | G57: 1330000000.0 | H57: 1149000000.0 | I57: 1049000000.0 | K57: Net Income From Continuing Operations | L57: 2927000000.0 | M57: 2540000000.0 | N57: 2245000000.0
F58: Investmentin Financial Assets | I58: 1049279535.388782
F59: Available For Sale Securities
F60: Financial Assets Designatedas Fair Value Through Profitor Loss Total
F61: Trading Securities | I61: 1049279535.388782
F62: Long Term Equity Investment | G62: 209000000.0 | H62: 203000000.0 | I62: 298000000.0
F63: Investmentsin Joint Venturesat Cost | G63: 1000000.0 | H63: 1000000.0 | I63: 104000000.0
F64: Investmentsin Associatesat Cost | G64: 208000000.0 | H64: 202000000.0 | I64: 194000000.0
F65: Goodwill And Other Intangible Assets | G65: 11686000000.0 | H65: 10224000000.0 | I65: 8585000000.0
F66: Other Intangible Assets | G66: 3999000000.0 | H66: 3325000000.0 | I66: 2480000000.0
F67: Goodwill | G67: 7687000000.0 | H67: 6899000000.0 | I67: 6105000000.0
F68: Net PPE | G68: 2946000000.0 | H68: 2555000000.0 | I68: 2158000000.0
F69: Accumulated Depreciation | G69: -2694000000.0 | H69: -2551000000.0 | I69: -2538000000.0
F70: Gross PPE | G70: 5640000000.0 | H70: 5106000000.0 | I70: 4696000000.0
F71: Machinery Furniture Equipment | G71: 4219000000.0 | H71: 3809000000.0 | I71: 3552000000.0
F72: Buildings And Improvements | G72: 911000000.0 | H72: 783000000.0 | I72: 685000000.0
F73: Land And Improvements | G73: 510000000.0 | H73: 514000000.0 | I73: 459000000.0
... F88: Cash Financial | G88: 476000000.0 | H88: 437000000.0 | I88: 382000000.0
